{"v":"5.7.14","fr":25,"ip":0,"op":83,"w":750,"h":700,"nm":"Comp 1","ddd":0,"assets":[],"layers":[{"ddd":0,"ind":1,"ty":4,"nm":"ojoDer","parent":5,"sr":1,"ks":{"o":{"a":0,"k":100,"ix":11},"r":{"a":0,"k":0,"ix":10},"p":{"a":0,"k":[60,-33,0],"ix":2,"l":2},"a":{"a":0,"k":[-22,-31,0],"ix":1,"l":2},"s":{"a":1,"k":[{"i":{"x":[0.833,0.833,0.833],"y":[0.833,0.833,0.833]},"o":{"x":[0.167,0.167,0.167],"y":[0.167,0.167,0.167]},"t":32,"s":[100,100,100]},{"i":{"x":[0.833,0.833,0.833],"y":[0.833,0.833,0.833]},"o":{"x":[0.167,0.167,0.167],"y":[0.167,0.167,0.167]},"t":42,"s":[100,33,100]},{"t":51,"s":[100,100,100]}],"ix":6,"l":2}},"ao":0,"sy":[{"c":{"a":0,"k":[0,0,0,1],"ix":2},"o":{"a":0,"k":75,"ix":3},"a":{"a":0,"k":120,"ix":5},"s":{"a":0,"k":5,"ix":8},"d":{"a":0,"k":5,"ix":6},"ch":{"a":0,"k":0,"ix":7},"bm":{"a":0,"k":5,"ix":1},"no":{"a":0,"k":0,"ix":9},"lc":{"a":0,"k":1,"ix":10},"ty":1,"nm":"Drop Shadow"},{"c":{"a":0,"k":[0,0,0,1],"ix":2},"o":{"a":0,"k":75,"ix":3},"a":{"a":0,"k":120,"ix":5},"s":{"a":0,"k":5,"ix":8},"d":{"a":0,"k":5,"ix":6},"ch":{"a":0,"k":0,"ix":7},"bm":{"a":0,"k":5,"ix":1},"no":{"a":0,"k":0,"ix":9},"ty":2,"nm":"Inner Shadow"},{"c":{"a":0,"k":[1,1,0.745098039216,1],"ix":5},"o":{"a":0,"k":75,"ix":2},"s":{"a":0,"k":5,"ix":10},"r":{"a":0,"k":50,"ix":11},"ch":{"a":0,"k":0,"ix":9},"bm":{"a":0,"k":11,"ix":1},"no":{"a":0,"k":0,"ix":3},"j":{"a":0,"k":0,"ix":12},"ty":3,"nm":"Outer Glow"},{"c":{"a":0,"k":[1,1,0.745098039216,1],"ix":5},"o":{"a":0,"k":75,"ix":2},"s":{"a":0,"k":5,"ix":11},"r":{"a":0,"k":50,"ix":12},"sr":{"a":0,"k":1,"ix":9},"ch":{"a":0,"k":0,"ix":10},"bm":{"a":0,"k":11,"ix":1},"no":{"a":0,"k":0,"ix":3},"j":{"a":0,"k":0,"ix":13},"ty":4,"nm":"Inner Glow"},{"bs":{"a":0,"k":2,"ix":1},"bt":{"a":0,"k":1,"ix":2},"sr":{"a":0,"k":100,"ix":3},"bd":{"a":0,"k":1,"ix":4},"s":{"a":0,"k":5,"ix":5},"so":{"a":0,"k":75,"ix":15},"ga":{"a":0,"k":0,"ix":7},"a":{"a":0,"k":120,"ix":8},"ll":{"a":0,"k":30,"ix":9},"hm":{"a":0,"k":11,"ix":10},"hc":{"a":0,"k":[1,1,1,1],"ix":11},"ho":{"a":0,"k":75,"ix":12},"sm":{"a":0,"k":5,"ix":13},"sc":{"a":0,"k":[0,0,0,1],"ix":14},"ty":5,"nm":"Bevel and Emboss"},{"bm":{"a":0,"k":5,"ix":1},"c":{"a":0,"k":[0,0,0,1],"ix":2},"o":{"a":0,"k":50,"ix":3},"a":{"a":0,"k":19,"ix":4},"d":{"a":0,"k":11,"ix":5},"s":{"a":0,"k":14,"ix":6},"in":{"a":0,"k":1,"ix":7},"ty":6,"nm":"Satin"},{"bm":{"a":0,"k":1,"ix":1},"c":{"a":0,"k":[1,0,0,1],"ix":2},"so":{"a":0,"k":100,"ix":3},"ty":7,"nm":"Color Overlay"},{"bm":{"a":0,"k":1,"ix":1},"o":{"a":0,"k":100,"ix":2},"gf":{"a":0,"ix":3},"gs":{"a":0,"k":100,"ix":4},"a":{"a":0,"k":90,"ix":5},"gt":{"a":0,"k":1,"ix":6},"re":{"a":0,"k":0,"ix":7},"al":{"a":0,"k":1,"ix":8},"s":{"a":0,"k":100,"ix":9},"of":{"a":0,"k":[0,0],"ix":10},"ty":8,"nm":"Gradient Overlay"},{"c":{"a":0,"k":[1,0,0,1],"ix":2},"s":{"a":0,"k":3,"ix":3},"ty":0,"nm":"Stroke"}],"shapes":[{"ty":"gr","it":[{"d":1,"ty":"el","s":{"a":0,"k":[30,30],"ix":2},"p":{"a":0,"k":[0,0],"ix":3},"nm":"Ellipse Path 1","mn":"ADBE Vector Shape - Ellipse","hd":false},{"ty":"st","c":{"a":0,"k":[1,1,1,1],"ix":3},"o":{"a":0,"k":100,"ix":4},"w":{"a":0,"k":0,"ix":5},"lc":1,"lj":1,"ml":4,"bm":0,"nm":"Stroke 1","mn":"ADBE Vector Graphic - Stroke","hd":false},{"ty":"fl","c":{"a":0,"k":[0,0.827450990677,0.509803950787,1],"ix":4},"o":{"a":0,"k":100,"ix":5},"r":1,"bm":0,"nm":"Fill 1","mn":"ADBE Vector Graphic - Fill","hd":false},{"ty":"tr","p":{"a":0,"k":[-22,-32],"ix":2},"a":{"a":0,"k":[0,0],"ix":1},"s":{"a":0,"k":[100,100],"ix":3},"r":{"a":0,"k":0,"ix":6},"o":{"a":0,"k":100,"ix":7},"sk":{"a":0,"k":0,"ix":4},"sa":{"a":0,"k":0,"ix":5},"nm":"Transform"}],"nm":"Ellipse 1","np":3,"cix":2,"bm":0,"ix":1,"mn":"ADBE Vector Group","hd":false}],"ip":0,"op":84,"st":0,"bm":0},{"ddd":0,"ind":2,"ty":4,"nm":"ojoIZQ","parent":5,"sr":1,"ks":{"o":{"a":0,"k":100,"ix":11},"r":{"a":0,"k":0,"ix":10},"p":{"a":0,"k":[4,-2,0],"ix":2,"l":2},"a":{"a":0,"k":[0,0,0],"ix":1,"l":2},"s":{"a":0,"k":[100,100,100],"ix":6,"l":2}},"ao":0,"sy":[{"c":{"a":0,"k":[0,0,0,1],"ix":2},"o":{"a":0,"k":75,"ix":3},"a":{"a":0,"k":120,"ix":5},"s":{"a":0,"k":5,"ix":8},"d":{"a":0,"k":5,"ix":6},"ch":{"a":0,"k":0,"ix":7},"bm":{"a":0,"k":5,"ix":1},"no":{"a":0,"k":0,"ix":9},"lc":{"a":0,"k":1,"ix":10},"ty":1,"nm":"Drop Shadow"},{"c":{"a":0,"k":[0,0,0,1],"ix":2},"o":{"a":0,"k":75,"ix":3},"a":{"a":0,"k":120,"ix":5},"s":{"a":0,"k":5,"ix":8},"d":{"a":0,"k":5,"ix":6},"ch":{"a":0,"k":0,"ix":7},"bm":{"a":0,"k":5,"ix":1},"no":{"a":0,"k":0,"ix":9},"ty":2,"nm":"Inner Shadow"},{"c":{"a":0,"k":[1,1,0.745098039216,1],"ix":5},"o":{"a":0,"k":75,"ix":2},"s":{"a":0,"k":5,"ix":10},"r":{"a":0,"k":50,"ix":11},"ch":{"a":0,"k":0,"ix":9},"bm":{"a":0,"k":11,"ix":1},"no":{"a":0,"k":0,"ix":3},"j":{"a":0,"k":0,"ix":12},"ty":3,"nm":"Outer Glow"},{"c":{"a":0,"k":[1,1,0.745098039216,1],"ix":5},"o":{"a":0,"k":75,"ix":2},"s":{"a":0,"k":5,"ix":11},"r":{"a":0,"k":50,"ix":12},"sr":{"a":0,"k":1,"ix":9},"ch":{"a":0,"k":0,"ix":10},"bm":{"a":0,"k":11,"ix":1},"no":{"a":0,"k":0,"ix":3},"j":{"a":0,"k":0,"ix":13},"ty":4,"nm":"Inner Glow"},{"bs":{"a":0,"k":2,"ix":1},"bt":{"a":0,"k":1,"ix":2},"sr":{"a":0,"k":100,"ix":3},"bd":{"a":0,"k":1,"ix":4},"s":{"a":0,"k":5,"ix":5},"so":{"a":0,"k":75,"ix":15},"ga":{"a":0,"k":0,"ix":7},"a":{"a":0,"k":120,"ix":8},"ll":{"a":0,"k":30,"ix":9},"hm":{"a":0,"k":11,"ix":10},"hc":{"a":0,"k":[1,1,1,1],"ix":11},"ho":{"a":0,"k":75,"ix":12},"sm":{"a":0,"k":5,"ix":13},"sc":{"a":0,"k":[0,0,0,1],"ix":14},"ty":5,"nm":"Bevel and Emboss"},{"bm":{"a":0,"k":5,"ix":1},"c":{"a":0,"k":[0,0,0,1],"ix":2},"o":{"a":0,"k":50,"ix":3},"a":{"a":0,"k":19,"ix":4},"d":{"a":0,"k":11,"ix":5},"s":{"a":0,"k":14,"ix":6},"in":{"a":0,"k":1,"ix":7},"ty":6,"nm":"Satin"},{"bm":{"a":0,"k":1,"ix":1},"c":{"a":0,"k":[1,0,0,1],"ix":2},"so":{"a":0,"k":100,"ix":3},"ty":7,"nm":"Color Overlay"},{"bm":{"a":0,"k":1,"ix":1},"o":{"a":0,"k":100,"ix":2},"gf":{"a":0,"ix":3},"gs":{"a":0,"k":100,"ix":4},"a":{"a":0,"k":90,"ix":5},"gt":{"a":0,"k":1,"ix":6},"re":{"a":0,"k":0,"ix":7},"al":{"a":0,"k":1,"ix":8},"s":{"a":0,"k":100,"ix":9},"of":{"a":0,"k":[0,0],"ix":10},"ty":8,"nm":"Gradient Overlay"},{"c":{"a":0,"k":[1,0,0,1],"ix":2},"s":{"a":0,"k":3,"ix":3},"ty":0,"nm":"Stroke"}],"shapes":[{"ty":"gr","it":[{"d":1,"ty":"el","s":{"a":0,"k":[30,30],"ix":2},"p":{"a":0,"k":[0,0],"ix":3},"nm":"Ellipse Path 1","mn":"ADBE Vector Shape - Ellipse","hd":false},{"ty":"st","c":{"a":0,"k":[1,1,1,1],"ix":3},"o":{"a":0,"k":100,"ix":4},"w":{"a":0,"k":0,"ix":5},"lc":1,"lj":1,"ml":4,"bm":0,"nm":"Stroke 1","mn":"ADBE Vector Graphic - Stroke","hd":false},{"ty":"fl","c":{"a":0,"k":[0,0.827450990677,0.509803950787,1],"ix":4},"o":{"a":0,"k":100,"ix":5},"r":1,"bm":0,"nm":"Fill 1","mn":"ADBE Vector Graphic - Fill","hd":false},{"ty":"tr","p":{"a":0,"k":[-22,-32],"ix":2},"a":{"a":0,"k":[0,0],"ix":1},"s":{"a":0,"k":[100,100],"ix":3},"r":{"a":0,"k":0,"ix":6},"o":{"a":0,"k":100,"ix":7},"sk":{"a":0,"k":0,"ix":4},"sa":{"a":0,"k":0,"ix":5},"nm":"Transform"}],"nm":"Ellipse 1","np":3,"cix":2,"bm":0,"ix":1,"mn":"ADBE Vector Group","hd":false}],"ip":0,"op":84,"st":0,"bm":0},{"ddd":0,"ind":3,"ty":4,"nm":"boca","parent":5,"sr":1,"ks":{"o":{"a":0,"k":100,"ix":11},"r":{"a":0,"k":0,"ix":10},"p":{"a":0,"k":[27,86,0],"ix":2,"l":2},"a":{"a":0,"k":[27,86,0],"ix":1,"l":2},"s":{"a":1,"k":[{"i":{"x":[0.833,0.833,0.833],"y":[0.833,0.833,0.833]},"o":{"x":[0.167,0.167,0.167],"y":[0.167,0.167,0.167]},"t":32,"s":[66,72,100]},{"t":57,"s":[124,121,100]}],"ix":6,"l":2}},"ao":0,"sy":[{"c":{"a":0,"k":[0,0,0,1],"ix":2},"o":{"a":0,"k":75,"ix":3},"a":{"a":0,"k":120,"ix":5},"s":{"a":0,"k":5,"ix":8},"d":{"a":0,"k":5,"ix":6},"ch":{"a":0,"k":0,"ix":7},"bm":{"a":0,"k":5,"ix":1},"no":{"a":0,"k":0,"ix":9},"lc":{"a":0,"k":1,"ix":10},"ty":1,"nm":"Drop Shadow"},{"c":{"a":0,"k":[0,0,0,1],"ix":2},"o":{"a":0,"k":75,"ix":3},"a":{"a":0,"k":120,"ix":5},"s":{"a":0,"k":5,"ix":8},"d":{"a":0,"k":5,"ix":6},"ch":{"a":0,"k":0,"ix":7},"bm":{"a":0,"k":5,"ix":1},"no":{"a":0,"k":0,"ix":9},"ty":2,"nm":"Inner Shadow"},{"c":{"a":0,"k":[1,1,0.745098039216,1],"ix":5},"o":{"a":0,"k":75,"ix":2},"s":{"a":0,"k":5,"ix":10},"r":{"a":0,"k":50,"ix":11},"ch":{"a":0,"k":0,"ix":9},"bm":{"a":0,"k":11,"ix":1},"no":{"a":0,"k":0,"ix":3},"j":{"a":0,"k":0,"ix":12},"ty":3,"nm":"Outer Glow"},{"c":{"a":0,"k":[1,1,0.745098039216,1],"ix":5},"o":{"a":0,"k":75,"ix":2},"s":{"a":0,"k":5,"ix":11},"r":{"a":0,"k":50,"ix":12},"sr":{"a":0,"k":1,"ix":9},"ch":{"a":0,"k":0,"ix":10},"bm":{"a":0,"k":11,"ix":1},"no":{"a":0,"k":0,"ix":3},"j":{"a":0,"k":0,"ix":13},"ty":4,"nm":"Inner Glow"},{"bs":{"a":0,"k":2,"ix":1},"bt":{"a":0,"k":1,"ix":2},"sr":{"a":0,"k":100,"ix":3},"bd":{"a":0,"k":1,"ix":4},"s":{"a":0,"k":5,"ix":5},"so":{"a":0,"k":75,"ix":15},"ga":{"a":0,"k":0,"ix":7},"a":{"a":0,"k":120,"ix":8},"ll":{"a":0,"k":30,"ix":9},"hm":{"a":0,"k":11,"ix":10},"hc":{"a":0,"k":[1,1,1,1],"ix":11},"ho":{"a":0,"k":75,"ix":12},"sm":{"a":0,"k":5,"ix":13},"sc":{"a":0,"k":[0,0,0,1],"ix":14},"ty":5,"nm":"Bevel and Emboss"},{"bm":{"a":0,"k":5,"ix":1},"c":{"a":0,"k":[0,0,0,1],"ix":2},"o":{"a":0,"k":50,"ix":3},"a":{"a":0,"k":19,"ix":4},"d":{"a":0,"k":11,"ix":5},"s":{"a":0,"k":14,"ix":6},"in":{"a":0,"k":1,"ix":7},"ty":6,"nm":"Satin"},{"bm":{"a":0,"k":1,"ix":1},"c":{"a":0,"k":[1,0,0,1],"ix":2},"so":{"a":0,"k":100,"ix":3},"ty":7,"nm":"Color Overlay"},{"bm":{"a":0,"k":1,"ix":1},"o":{"a":0,"k":100,"ix":2},"gf":{"a":0,"ix":3},"gs":{"a":0,"k":100,"ix":4},"a":{"a":0,"k":90,"ix":5},"gt":{"a":0,"k":1,"ix":6},"re":{"a":0,"k":0,"ix":7},"al":{"a":0,"k":1,"ix":8},"s":{"a":0,"k":100,"ix":9},"of":{"a":0,"k":[0,0],"ix":10},"ty":8,"nm":"Gradient Overlay"},{"c":{"a":0,"k":[1,0,0,1],"ix":2},"s":{"a":0,"k":3,"ix":3},"ty":0,"nm":"Stroke"}],"shapes":[{"ty":"gr","it":[{"ind":0,"ty":"sh","ix":1,"ks":{"a":0,"k":{"i":[[-13.096,6.266],[-0.843,-0.167],[0.345,-1.363],[1.062,-0.921],[15.365,10.017],[-1.184,2.266],[-3.796,-1.113]],"o":[[0.776,-0.371],[1.379,0.273],[-0.346,1.363],[-14.216,12.319],[-2.142,-1.396],[3.55,-1.746],[14.173,4.157]],"v":[[49.283,74.557],[51.745,73.965],[53.468,77.315],[50.998,80.65],[2.151,83.719],[-1.123,77.577],[10.417,78.413]],"c":true},"ix":2},"nm":"Path 1","mn":"ADBE Vector Shape - Group","hd":false},{"ty":"fl","c":{"a":0,"k":[0,0.827450990677,0.509803950787,1],"ix":4},"o":{"a":0,"k":100,"ix":5},"r":1,"bm":0,"nm":"Fill 1","mn":"ADBE Vector Graphic - Fill","hd":false},{"ty":"tr","p":{"a":0,"k":[0,0],"ix":2},"a":{"a":0,"k":[0,0],"ix":1},"s":{"a":0,"k":[100,100],"ix":3},"r":{"a":0,"k":0,"ix":6},"o":{"a":0,"k":100,"ix":7},"sk":{"a":0,"k":0,"ix":4},"sa":{"a":0,"k":0,"ix":5},"nm":"Transform"}],"nm":"Group 1","np":2,"cix":2,"bm":0,"ix":1,"mn":"ADBE Vector Group","hd":false}],"ip":0,"op":84,"st":0,"bm":0},{"ddd":0,"ind":4,"ty":4,"nm":"nariz","parent":5,"sr":1,"ks":{"o":{"a":0,"k":100,"ix":11},"r":{"a":0,"k":0,"ix":10},"p":{"a":0,"k":[0,0,0],"ix":2,"l":2},"a":{"a":0,"k":[0,0,0],"ix":1,"l":2},"s":{"a":0,"k":[100,100,100],"ix":6,"l":2}},"ao":0,"sy":[{"c":{"a":0,"k":[0,0,0,1],"ix":2},"o":{"a":0,"k":75,"ix":3},"a":{"a":0,"k":120,"ix":5},"s":{"a":0,"k":5,"ix":8},"d":{"a":0,"k":5,"ix":6},"ch":{"a":0,"k":0,"ix":7},"bm":{"a":0,"k":5,"ix":1},"no":{"a":0,"k":0,"ix":9},"lc":{"a":0,"k":1,"ix":10},"ty":1,"nm":"Drop Shadow"},{"c":{"a":0,"k":[0,0,0,1],"ix":2},"o":{"a":0,"k":75,"ix":3},"a":{"a":0,"k":120,"ix":5},"s":{"a":0,"k":5,"ix":8},"d":{"a":0,"k":5,"ix":6},"ch":{"a":0,"k":0,"ix":7},"bm":{"a":0,"k":5,"ix":1},"no":{"a":0,"k":0,"ix":9},"ty":2,"nm":"Inner Shadow"},{"c":{"a":0,"k":[1,1,0.745098039216,1],"ix":5},"o":{"a":0,"k":75,"ix":2},"s":{"a":0,"k":5,"ix":10},"r":{"a":0,"k":50,"ix":11},"ch":{"a":0,"k":0,"ix":9},"bm":{"a":0,"k":11,"ix":1},"no":{"a":0,"k":0,"ix":3},"j":{"a":0,"k":0,"ix":12},"ty":3,"nm":"Outer Glow"},{"c":{"a":0,"k":[1,1,0.745098039216,1],"ix":5},"o":{"a":0,"k":75,"ix":2},"s":{"a":0,"k":5,"ix":11},"r":{"a":0,"k":50,"ix":12},"sr":{"a":0,"k":1,"ix":9},"ch":{"a":0,"k":0,"ix":10},"bm":{"a":0,"k":11,"ix":1},"no":{"a":0,"k":0,"ix":3},"j":{"a":0,"k":0,"ix":13},"ty":4,"nm":"Inner Glow"},{"bs":{"a":0,"k":2,"ix":1},"bt":{"a":0,"k":1,"ix":2},"sr":{"a":0,"k":100,"ix":3},"bd":{"a":0,"k":1,"ix":4},"s":{"a":0,"k":5,"ix":5},"so":{"a":0,"k":75,"ix":15},"ga":{"a":0,"k":0,"ix":7},"a":{"a":0,"k":120,"ix":8},"ll":{"a":0,"k":30,"ix":9},"hm":{"a":0,"k":11,"ix":10},"hc":{"a":0,"k":[1,1,1,1],"ix":11},"ho":{"a":0,"k":75,"ix":12},"sm":{"a":0,"k":5,"ix":13},"sc":{"a":0,"k":[0,0,0,1],"ix":14},"ty":5,"nm":"Bevel and Emboss"},{"bm":{"a":0,"k":5,"ix":1},"c":{"a":0,"k":[0,0,0,1],"ix":2},"o":{"a":0,"k":50,"ix":3},"a":{"a":0,"k":19,"ix":4},"d":{"a":0,"k":11,"ix":5},"s":{"a":0,"k":14,"ix":6},"in":{"a":0,"k":1,"ix":7},"ty":6,"nm":"Satin"},{"bm":{"a":0,"k":1,"ix":1},"c":{"a":0,"k":[1,0,0,1],"ix":2},"so":{"a":0,"k":100,"ix":3},"ty":7,"nm":"Color Overlay"},{"bm":{"a":0,"k":1,"ix":1},"o":{"a":0,"k":100,"ix":2},"gf":{"a":0,"ix":3},"gs":{"a":0,"k":100,"ix":4},"a":{"a":0,"k":90,"ix":5},"gt":{"a":0,"k":1,"ix":6},"re":{"a":0,"k":0,"ix":7},"al":{"a":0,"k":1,"ix":8},"s":{"a":0,"k":100,"ix":9},"of":{"a":0,"k":[0,0],"ix":10},"ty":8,"nm":"Gradient Overlay"},{"c":{"a":0,"k":[1,0,0,1],"ix":2},"s":{"a":0,"k":3,"ix":3},"ty":0,"nm":"Stroke"}],"shapes":[{"ty":"gr","it":[{"ind":0,"ty":"sh","ix":1,"ks":{"a":0,"k":{"i":[[0,0],[0,0],[0,0],[0,0]],"o":[[0,0],[0,0],[0,0],[0,0]],"v":[[38.127,43.959],[20.17,43.959],[20.17,19.552],[20.17,-2.791]],"c":false},"ix":2},"nm":"Path 1","mn":"ADBE Vector Shape - Group","hd":false},{"ty":"st","c":{"a":0,"k":[0,0.827450990677,0.509803950787,1],"ix":3},"o":{"a":0,"k":100,"ix":4},"w":{"a":0,"k":8.838,"ix":5},"lc":2,"lj":2,"bm":0,"nm":"Stroke 1","mn":"ADBE Vector Graphic - Stroke","hd":false},{"ty":"tr","p":{"a":0,"k":[0,0],"ix":2},"a":{"a":0,"k":[0,0],"ix":1},"s":{"a":0,"k":[100,100],"ix":3},"r":{"a":0,"k":0,"ix":6},"o":{"a":0,"k":100,"ix":7},"sk":{"a":0,"k":0,"ix":4},"sa":{"a":0,"k":0,"ix":5},"nm":"Transform"}],"nm":"Group 1","np":2,"cix":2,"bm":0,"ix":1,"mn":"ADBE Vector Group","hd":false}],"ip":0,"op":84,"st":0,"bm":0},{"ddd":0,"ind":5,"ty":4,"nm":"torso","sr":1,"ks":{"o":{"a":0,"k":100,"ix":11},"r":{"a":0,"k":0,"ix":10},"p":{"a":1,"k":[{"i":{"x":0.667,"y":1},"o":{"x":0.167,"y":0.167},"t":3,"s":[375,919,0],"to":[0,-97.667,0],"ti":[0,94.5,0]},{"i":{"x":0.833,"y":0.833},"o":{"x":0.167,"y":0.167},"t":15,"s":[375,333,0],"to":[0,-94.5,0],"ti":[0,-1.5,0]},{"i":{"x":0.833,"y":0.833},"o":{"x":0.333,"y":0},"t":22,"s":[375,352,0],"to":[0,1.5,0],"ti":[0,0.167,0]},{"i":{"x":0.833,"y":0.833},"o":{"x":0.167,"y":0.167},"t":29,"s":[375,342,0],"to":[0,-0.167,0],"ti":[0,-0.833,0]},{"i":{"x":0.833,"y":0.833},"o":{"x":0.167,"y":0.167},"t":34,"s":[375,351,0],"to":[0,0.833,0],"ti":[0,0.667,0]},{"i":{"x":0.833,"y":0.833},"o":{"x":0.167,"y":0.167},"t":44,"s":[375,347,0],"to":[0,0,0],"ti":[0,0,0]},{"t":68,"s":[375,347,0]}],"ix":2,"l":2},"a":{"a":0,"k":[0,0,0],"ix":1,"l":2},"s":{"a":0,"k":[100,100,100],"ix":6,"l":2}},"ao":0,"hasMask":true,"masksProperties":[{"inv":false,"mode":"a","pt":{"a":0,"k":{"i":[[0,0],[0,0],[0,0],[0,0]],"o":[[0,0],[0,0],[0,0],[0,0]],"v":[[366.444,514.121],[-315.382,514.121],[-315.382,-304.913],[366.444,-304.913]],"c":true},"ix":1},"o":{"a":0,"k":100,"ix":3},"x":{"a":0,"k":0,"ix":4},"nm":"Mask 1"}],"sy":[{"c":{"a":0,"k":[0,0,0,1],"ix":2},"o":{"a":0,"k":75,"ix":3},"a":{"a":0,"k":120,"ix":5},"s":{"a":0,"k":5,"ix":8},"d":{"a":0,"k":5,"ix":6},"ch":{"a":0,"k":0,"ix":7},"bm":{"a":0,"k":5,"ix":1},"no":{"a":0,"k":0,"ix":9},"lc":{"a":0,"k":1,"ix":10},"ty":1,"nm":"Drop Shadow"},{"c":{"a":0,"k":[0,0,0,1],"ix":2},"o":{"a":0,"k":75,"ix":3},"a":{"a":0,"k":120,"ix":5},"s":{"a":0,"k":5,"ix":8},"d":{"a":0,"k":5,"ix":6},"ch":{"a":0,"k":0,"ix":7},"bm":{"a":0,"k":5,"ix":1},"no":{"a":0,"k":0,"ix":9},"ty":2,"nm":"Inner Shadow"},{"c":{"a":0,"k":[1,1,0.745098039216,1],"ix":5},"o":{"a":0,"k":75,"ix":2},"s":{"a":0,"k":5,"ix":10},"r":{"a":0,"k":50,"ix":11},"ch":{"a":0,"k":0,"ix":9},"bm":{"a":0,"k":11,"ix":1},"no":{"a":0,"k":0,"ix":3},"j":{"a":0,"k":0,"ix":12},"ty":3,"nm":"Outer Glow"},{"c":{"a":0,"k":[1,1,0.745098039216,1],"ix":5},"o":{"a":0,"k":75,"ix":2},"s":{"a":0,"k":5,"ix":11},"r":{"a":0,"k":50,"ix":12},"sr":{"a":0,"k":1,"ix":9},"ch":{"a":0,"k":0,"ix":10},"bm":{"a":0,"k":11,"ix":1},"no":{"a":0,"k":0,"ix":3},"j":{"a":0,"k":0,"ix":13},"ty":4,"nm":"Inner Glow"},{"bs":{"a":0,"k":2,"ix":1},"bt":{"a":0,"k":1,"ix":2},"sr":{"a":0,"k":100,"ix":3},"bd":{"a":0,"k":1,"ix":4},"s":{"a":0,"k":5,"ix":5},"so":{"a":0,"k":75,"ix":15},"ga":{"a":0,"k":0,"ix":7},"a":{"a":0,"k":120,"ix":8},"ll":{"a":0,"k":30,"ix":9},"hm":{"a":0,"k":11,"ix":10},"hc":{"a":0,"k":[1,1,1,1],"ix":11},"ho":{"a":0,"k":75,"ix":12},"sm":{"a":0,"k":5,"ix":13},"sc":{"a":0,"k":[0,0,0,1],"ix":14},"ty":5,"nm":"Bevel and Emboss"},{"bm":{"a":0,"k":5,"ix":1},"c":{"a":0,"k":[0,0,0,1],"ix":2},"o":{"a":0,"k":50,"ix":3},"a":{"a":0,"k":19,"ix":4},"d":{"a":0,"k":11,"ix":5},"s":{"a":0,"k":14,"ix":6},"in":{"a":0,"k":1,"ix":7},"ty":6,"nm":"Satin"},{"bm":{"a":0,"k":1,"ix":1},"c":{"a":0,"k":[1,0,0,1],"ix":2},"so":{"a":0,"k":100,"ix":3},"ty":7,"nm":"Color Overlay"},{"bm":{"a":0,"k":1,"ix":1},"o":{"a":0,"k":100,"ix":2},"gf":{"a":0,"ix":3},"gs":{"a":0,"k":100,"ix":4},"a":{"a":0,"k":90,"ix":5},"gt":{"a":0,"k":1,"ix":6},"re":{"a":0,"k":0,"ix":7},"al":{"a":0,"k":1,"ix":8},"s":{"a":0,"k":100,"ix":9},"of":{"a":0,"k":[0,0],"ix":10},"ty":8,"nm":"Gradient Overlay"},{"c":{"a":0,"k":[1,0,0,1],"ix":2},"s":{"a":0,"k":3,"ix":3},"ty":0,"nm":"Stroke"}],"shapes":[{"ty":"gr","it":[{"ty":"gr","it":[{"ty":"gr","it":[{"ind":0,"ty":"sh","ix":1,"ks":{"a":0,"k":{"i":[[0,-4.026],[4.026,0],[0,4.027],[-4.027,0]],"o":[[0,4.027],[-4.027,0],[0,-4.026],[4.026,0]],"v":[[32.045,305.808],[24.755,313.098],[17.464,305.808],[24.755,298.517]],"c":true},"ix":2},"nm":"Path 1","mn":"ADBE Vector Shape - Group","hd":false},{"ty":"fl","c":{"a":0,"k":[0,0.215686276555,0.698039233685,1],"ix":4},"o":{"a":0,"k":100,"ix":5},"r":1,"bm":0,"nm":"Fill 1","mn":"ADBE Vector Graphic - Fill","hd":false},{"ty":"tr","p":{"a":0,"k":[0,0],"ix":2},"a":{"a":0,"k":[0,0],"ix":1},"s":{"a":0,"k":[100,100],"ix":3},"r":{"a":0,"k":0,"ix":6},"o":{"a":0,"k":100,"ix":7},"sk":{"a":0,"k":0,"ix":4},"sa":{"a":0,"k":0,"ix":5},"nm":"Transform"}],"nm":"Group 1","np":2,"cix":2,"bm":0,"ix":1,"mn":"ADBE Vector Group","hd":false},{"ty":"gr","it":[{"ind":0,"ty":"sh","ix":1,"ks":{"a":0,"k":{"i":[[0,-4.026],[4.026,0],[0,4.027],[-4.027,0]],"o":[[0,4.027],[-4.027,0],[0,-4.026],[4.026,0]],"v":[[32.045,247.483],[24.755,254.774],[17.464,247.483],[24.755,240.193]],"c":true},"ix":2},"nm":"Path 1","mn":"ADBE Vector Shape - Group","hd":false},{"ty":"fl","c":{"a":0,"k":[0,0.215686276555,0.698039233685,1],"ix":4},"o":{"a":0,"k":100,"ix":5},"r":1,"bm":0,"nm":"Fill 1","mn":"ADBE Vector Graphic - Fill","hd":false},{"ty":"tr","p":{"a":0,"k":[0,0],"ix":2},"a":{"a":0,"k":[0,0],"ix":1},"s":{"a":0,"k":[100,100],"ix":3},"r":{"a":0,"k":0,"ix":6},"o":{"a":0,"k":100,"ix":7},"sk":{"a":0,"k":0,"ix":4},"sa":{"a":0,"k":0,"ix":5},"nm":"Transform"}],"nm":"Group 2","np":2,"cix":2,"bm":0,"ix":2,"mn":"ADBE Vector Group","hd":false},{"ty":"gr","it":[{"ind":0,"ty":"sh","ix":1,"ks":{"a":0,"k":{"i":[[0,0],[0,0],[0,0],[0,0],[0,0]],"o":[[0,0],[0,0],[0,0],[0,0],[0,0]],"v":[[9.562,213.19],[9.562,349.168],[38.631,349.168],[38.631,212.846],[25.576,212.846]],"c":true},"ix":2},"nm":"Path 1","mn":"ADBE Vector Shape - Group","hd":false},{"ty":"fl","c":{"a":0,"k":[0,0.827450990677,0.509803950787,1],"ix":4},"o":{"a":0,"k":100,"ix":5},"r":1,"bm":0,"nm":"Fill 1","mn":"ADBE Vector Graphic - Fill","hd":false},{"ty":"tr","p":{"a":0,"k":[0,0],"ix":2},"a":{"a":0,"k":[0,0],"ix":1},"s":{"a":0,"k":[100,100],"ix":3},"r":{"a":0,"k":0,"ix":6},"o":{"a":0,"k":100,"ix":7},"sk":{"a":0,"k":0,"ix":4},"sa":{"a":0,"k":0,"ix":5},"nm":"Transform"}],"nm":"Group 3","np":2,"cix":2,"bm":0,"ix":3,"mn":"ADBE Vector Group","hd":false},{"ty":"gr","it":[{"ty":"gr","it":[{"ty":"gr","it":[{"ty":"gr","it":[{"ind":0,"ty":"sh","ix":1,"ks":{"a":0,"k":{"i":[[4.527,-0.642],[0,0],[0.643,4.527],[-4.527,0.642],[0,0],[-0.642,-4.527]],"o":[[0,0],[-4.527,0.642],[-0.642,-4.527],[0,0],[4.527,-0.642],[0.643,4.527]],"v":[[65.852,138.284],[58.427,139.336],[49.068,132.303],[56.102,122.944],[63.528,121.892],[72.885,128.925]],"c":true},"ix":2},"nm":"Path 1","mn":"ADBE Vector Shape - Group","hd":false},{"ty":"fl","c":{"a":0,"k":[1,1,1,1],"ix":4},"o":{"a":0,"k":100,"ix":5},"r":1,"bm":0,"nm":"Fill 1","mn":"ADBE Vector Graphic - Fill","hd":false},{"ty":"tr","p":{"a":0,"k":[0,0],"ix":2},"a":{"a":0,"k":[0,0],"ix":1},"s":{"a":0,"k":[100,100],"ix":3},"r":{"a":0,"k":0,"ix":6},"o":{"a":0,"k":100,"ix":7},"sk":{"a":0,"k":0,"ix":4},"sa":{"a":0,"k":0,"ix":5},"nm":"Transform"}],"nm":"Group 1","np":2,"cix":2,"bm":0,"ix":1,"mn":"ADBE Vector Group","hd":false},{"ty":"gr","it":[{"ind":0,"ty":"sh","ix":1,"ks":{"a":0,"k":{"i":[[0,0],[0,0],[12.454,-24.261],[10.914,-10.033],[16.813,-3.238],[0,0],[-11.78,11.169],[-6.386,17.672],[-0.022,0.138],[0,0]],"o":[[0,0],[-0.412,2.6],[-6.221,12.133],[-10.924,10.036],[0,0],[18.615,-3.574],[17.681,-16.765],[6.376,-17.679],[0,0],[0,0]],"v":[[143.183,22.061],[143.146,22.298],[126.225,72.66],[100.781,107.135],[59.562,128.188],[60.721,134.218],[106.051,110.613],[140.839,54.298],[149.256,22.966],[143.183,22.061]],"c":true},"ix":2},"nm":"Path 1","mn":"ADBE Vector Shape - Group","hd":false},{"ty":"fl","c":{"a":0,"k":[1,1,1,1],"ix":4},"o":{"a":0,"k":100,"ix":5},"r":1,"bm":0,"nm":"Fill 1","mn":"ADBE Vector Graphic - Fill","hd":false},{"ty":"tr","p":{"a":0,"k":[0,0],"ix":2},"a":{"a":0,"k":[0,0],"ix":1},"s":{"a":0,"k":[100,100],"ix":3},"r":{"a":0,"k":0,"ix":6},"o":{"a":0,"k":100,"ix":7},"sk":{"a":0,"k":0,"ix":4},"sa":{"a":0,"k":0,"ix":5},"nm":"Transform"}],"nm":"Group 2","np":2,"cix":2,"bm":0,"ix":2,"mn":"ADBE Vector Group","hd":false},{"ty":"tr","p":{"a":0,"k":[0,0],"ix":2},"a":{"a":0,"k":[0,0],"ix":1},"s":{"a":0,"k":[100,100],"ix":3},"r":{"a":0,"k":0,"ix":6},"o":{"a":0,"k":100,"ix":7},"sk":{"a":0,"k":0,"ix":4},"sa":{"a":0,"k":0,"ix":5},"nm":"Transform"}],"nm":"Group 1","np":2,"cix":2,"bm":0,"ix":1,"mn":"ADBE Vector Group","hd":false},{"ty":"gr","it":[{"ind":0,"ty":"sh","ix":1,"ks":{"a":0,"k":{"i":[[-8.564,-19.554],[0,22.317],[-6.324,2.087]],"o":[[-6.846,1.167],[0,-22.317],[0,0]],"v":[[-85.975,51.206],[-113.111,6.45],[-103.319,-29.159]],"c":true},"ix":2},"nm":"Path 1","mn":"ADBE Vector Shape - Group","hd":false},{"ty":"fl","c":{"a":0,"k":[0,0.827450990677,0.509803950787,1],"ix":4},"o":{"a":0,"k":100,"ix":5},"r":1,"bm":0,"nm":"Fill 1","mn":"ADBE Vector Graphic - Fill","hd":false},{"ty":"tr","p":{"a":0,"k":[0,0],"ix":2},"a":{"a":0,"k":[0,0],"ix":1},"s":{"a":0,"k":[100,100],"ix":3},"r":{"a":0,"k":0,"ix":6},"o":{"a":0,"k":100,"ix":7},"sk":{"a":0,"k":0,"ix":4},"sa":{"a":0,"k":0,"ix":5},"nm":"Transform"}],"nm":"Group 2","np":2,"cix":2,"bm":0,"ix":2,"mn":"ADBE Vector Group","hd":false},{"ty":"gr","it":[{"ind":0,"ty":"sh","ix":1,"ks":{"a":0,"k":{"i":[[6.938,0.522],[0.614,0.123],[-4.42,36.775],[-1.719,-18.602]],"o":[[-0.614,-0.031],[3.868,-15.042],[4.912,3.806],[2.087,22.225]],"v":[[136.763,46.571],[134.952,46.325],[149.533,-33.549],[159.602,-0.519]],"c":true},"ix":2},"nm":"Path 1","mn":"ADBE Vector Shape - Group","hd":false},{"ty":"fl","c":{"a":0,"k":[0,0.827450990677,0.509803950787,1],"ix":4},"o":{"a":0,"k":100,"ix":5},"r":1,"bm":0,"nm":"Fill 1","mn":"ADBE Vector Graphic - Fill","hd":false},{"ty":"tr","p":{"a":0,"k":[0,0],"ix":2},"a":{"a":0,"k":[0,0],"ix":1},"s":{"a":0,"k":[100,100],"ix":3},"r":{"a":0,"k":0,"ix":6},"o":{"a":0,"k":100,"ix":7},"sk":{"a":0,"k":0,"ix":4},"sa":{"a":0,"k":0,"ix":5},"nm":"Transform"}],"nm":"Group 3","np":2,"cix":2,"bm":0,"ix":3,"mn":"ADBE Vector Group","hd":false},{"ty":"gr","it":[{"ind":0,"ty":"sh","ix":1,"ks":{"a":0,"k":{"i":[[0,0],[0,21.872],[-105.829,-3.837],[-1.727,-20.721],[0,0]],"o":[[0,-31.42],[0,-21.872],[105.829,3.837],[1.727,20.721],[0,0]],"v":[[-93.634,-16.128],[-99.507,-77.714],[25.854,-159.779],[145.911,-80.592],[141.587,-18.721]],"c":false},"ix":2},"nm":"Path 1","mn":"ADBE Vector Shape - Group","hd":false},{"ty":"st","c":{"a":0,"k":[1,1,1,1],"ix":3},"o":{"a":0,"k":100,"ix":4},"w":{"a":0,"k":6.139,"ix":5},"lc":1,"lj":1,"ml":10,"bm":0,"nm":"Stroke 1","mn":"ADBE Vector Graphic - Stroke","hd":false},{"ty":"tr","p":{"a":0,"k":[0,0],"ix":2},"a":{"a":0,"k":[0,0],"ix":1},"s":{"a":0,"k":[100,100],"ix":3},"r":{"a":0,"k":0,"ix":6},"o":{"a":0,"k":100,"ix":7},"sk":{"a":0,"k":0,"ix":4},"sa":{"a":0,"k":0,"ix":5},"nm":"Transform"}],"nm":"Group 4","np":2,"cix":2,"bm":0,"ix":4,"mn":"ADBE Vector Group","hd":false},{"ty":"gr","it":[{"ind":0,"ty":"sh","ix":1,"ks":{"a":0,"k":{"i":[[0,0],[0,24.112],[-105.829,-4.23],[-1.727,-22.843],[0,0]],"o":[[0,-34.639],[0,-24.112],[105.829,4.23],[1.727,22.843],[0,0]],"v":[[-93.634,-16.128],[-99.507,-83.757],[25.854,-174.228],[145.911,-86.93],[141.587,-18.721]],"c":false},"ix":2},"nm":"Path 1","mn":"ADBE Vector Shape - Group","hd":false},{"ty":"st","c":{"a":0,"k":[1,1,1,1],"ix":3},"o":{"a":0,"k":100,"ix":4},"w":{"a":0,"k":6.139,"ix":5},"lc":1,"lj":1,"ml":10,"bm":0,"nm":"Stroke 1","mn":"ADBE Vector Graphic - Stroke","hd":false},{"ty":"tr","p":{"a":0,"k":[0,0],"ix":2},"a":{"a":0,"k":[0,0],"ix":1},"s":{"a":0,"k":[100,100],"ix":3},"r":{"a":0,"k":0,"ix":6},"o":{"a":0,"k":100,"ix":7},"sk":{"a":0,"k":0,"ix":4},"sa":{"a":0,"k":0,"ix":5},"nm":"Transform"}],"nm":"Group 5","np":2,"cix":2,"bm":0,"ix":5,"mn":"ADBE Vector Group","hd":false},{"ty":"gr","it":[{"ind":0,"ty":"sh","ix":1,"ks":{"a":0,"k":{"i":[[6.938,0.522],[0.614,0.123],[-0.829,3.898],[0,0],[-6.477,-1.473],[-0.921,-0.767],[-1.719,-18.602]],"o":[[-0.614,-0.031],[-6.293,-1.197],[0.921,-4.267],[-1.043,-11.112],[1.044,0.246],[4.912,3.806],[2.087,22.225]],"v":[[136.763,46.571],[134.952,46.325],[123.471,36.349],[130.286,-23.05],[146.555,-35.053],[149.533,-33.549],[159.602,-0.519]],"c":true},"ix":2},"nm":"Path 1","mn":"ADBE Vector Shape - Group","hd":false},{"ty":"fl","c":{"a":0,"k":[1,1,1,1],"ix":4},"o":{"a":0,"k":100,"ix":5},"r":1,"bm":0,"nm":"Fill 1","mn":"ADBE Vector Graphic - Fill","hd":false},{"ty":"tr","p":{"a":0,"k":[0,0],"ix":2},"a":{"a":0,"k":[0,0],"ix":1},"s":{"a":0,"k":[100,100],"ix":3},"r":{"a":0,"k":0,"ix":6},"o":{"a":0,"k":100,"ix":7},"sk":{"a":0,"k":0,"ix":4},"sa":{"a":0,"k":0,"ix":5},"nm":"Transform"}],"nm":"Group 6","np":2,"cix":2,"bm":0,"ix":6,"mn":"ADBE Vector Group","hd":false},{"ty":"gr","it":[{"ind":0,"ty":"sh","ix":1,"ks":{"a":0,"k":{"i":[[6.846,-1.136],[0,22.317],[-6.324,2.087],[0,-11.173],[-1.29,-4.175]],"o":[[-6.846,1.167],[0,-22.317],[6.354,-2.087],[0,0],[1.32,4.144]],"v":[[-85.975,51.206],[-113.111,6.45],[-103.319,-29.159],[-85.975,-18.722],[-73.696,39.817]],"c":true},"ix":2},"nm":"Path 1","mn":"ADBE Vector Shape - Group","hd":false},{"ty":"fl","c":{"a":0,"k":[1,1,1,1],"ix":4},"o":{"a":0,"k":100,"ix":5},"r":1,"bm":0,"nm":"Fill 1","mn":"ADBE Vector Graphic - Fill","hd":false},{"ty":"tr","p":{"a":0,"k":[0,0],"ix":2},"a":{"a":0,"k":[0,0],"ix":1},"s":{"a":0,"k":[100,100],"ix":3},"r":{"a":0,"k":0,"ix":6},"o":{"a":0,"k":100,"ix":7},"sk":{"a":0,"k":0,"ix":4},"sa":{"a":0,"k":0,"ix":5},"nm":"Transform"}],"nm":"Group 7","np":2,"cix":2,"bm":0,"ix":7,"mn":"ADBE Vector Group","hd":false},{"ty":"gr","it":[{"ind":0,"ty":"sh","ix":1,"ks":{"a":0,"k":{"i":[[2.296,-20.827],[0.724,-2.328],[0,0],[0,0],[0,0],[-10.445,5.348],[-14.377,16.454],[0.472,10.319]],"o":[[-0.252,2.391],[-7.016,22.651],[0,0],[0,0],[0,0],[7.991,-4.059],[6.795,-7.771],[0,0]],"v":[[108.536,161.848],[107.089,168.959],[57.382,252.36],[38.631,212.846],[31.993,189.313],[42.438,183.965],[87.363,147.66],[97.148,119.409]],"c":true},"ix":2},"nm":"Path 1","mn":"ADBE Vector Shape - Group","hd":false},{"ty":"st","c":{"a":0,"k":[0,0.827450990677,0.509803950787,1],"ix":3},"o":{"a":0,"k":100,"ix":4},"w":{"a":0,"k":11.425,"ix":5},"lc":2,"lj":2,"bm":0,"nm":"Stroke 1","mn":"ADBE Vector Graphic - Stroke","hd":false},{"ty":"fl","c":{"a":0,"k":[0,0.215686276555,0.698039233685,1],"ix":4},"o":{"a":0,"k":100,"ix":5},"r":1,"bm":0,"nm":"Fill 1","mn":"ADBE Vector Graphic - Fill","hd":false},{"ty":"tr","p":{"a":0,"k":[0,0],"ix":2},"a":{"a":0,"k":[0,0],"ix":1},"s":{"a":0,"k":[100,100],"ix":3},"r":{"a":0,"k":0,"ix":6},"o":{"a":0,"k":100,"ix":7},"sk":{"a":0,"k":0,"ix":4},"sa":{"a":0,"k":0,"ix":5},"nm":"Transform"}],"nm":"Group 8","np":3,"cix":2,"bm":0,"ix":8,"mn":"ADBE Vector Group","hd":false},{"ty":"gr","it":[{"ty":"gr","it":[{"ind":0,"ty":"sh","ix":1,"ks":{"a":0,"k":{"i":[[0,0],[0,0],[2.304,23.61],[0,0],[-6.795,-7.771],[-7.991,-4.059]],"o":[[0,0],[0,0],[-4.09,-41.903],[-0.472,10.319],[14.377,16.454],[10.476,5.348]],"v":[[19.189,189.313],[-6.231,252.36],[-59.65,164.239],[-45.996,119.409],[-36.212,147.66],[8.713,183.965]],"c":true},"ix":2},"nm":"Path 1","mn":"ADBE Vector Shape - Group","hd":false},{"ty":"st","c":{"a":0,"k":[0,0.827450990677,0.509803950787,1],"ix":3},"o":{"a":0,"k":100,"ix":4},"w":{"a":0,"k":11.425,"ix":5},"lc":2,"lj":2,"bm":0,"nm":"Stroke 1","mn":"ADBE Vector Graphic - Stroke","hd":false},{"ty":"fl","c":{"a":0,"k":[0,0.215686276555,0.698039233685,1],"ix":4},"o":{"a":0,"k":100,"ix":5},"r":1,"bm":0,"nm":"Fill 1","mn":"ADBE Vector Graphic - Fill","hd":false},{"ty":"tr","p":{"a":0,"k":[0,0],"ix":2},"a":{"a":0,"k":[0,0],"ix":1},"s":{"a":0,"k":[100,100],"ix":3},"r":{"a":0,"k":0,"ix":6},"o":{"a":0,"k":100,"ix":7},"sk":{"a":0,"k":0,"ix":4},"sa":{"a":0,"k":0,"ix":5},"nm":"Transform"}],"nm":"Group 1","np":3,"cix":2,"bm":0,"ix":1,"mn":"ADBE Vector Group","hd":false},{"ty":"tr","p":{"a":0,"k":[0,0],"ix":2},"a":{"a":0,"k":[0,0],"ix":1},"s":{"a":0,"k":[100,100],"ix":3},"r":{"a":0,"k":0,"ix":6},"o":{"a":0,"k":100,"ix":7},"sk":{"a":0,"k":0,"ix":4},"sa":{"a":0,"k":0,"ix":5},"nm":"Transform"}],"nm":"Group 9","np":1,"cix":2,"bm":0,"ix":9,"mn":"ADBE Vector Group","hd":false},{"ty":"gr","it":[{"ty":"gr","it":[{"ind":0,"ty":"sh","ix":1,"ks":{"a":0,"k":{"i":[[1.936,-26.79],[1.064,-12.364],[-1.118,-5.301],[0,0],[2.902,9.57],[0.137,-0.013],[0,0],[2.729,-10.857],[0,0],[0,0],[-7.796,64.331],[-12.416,3.583],[0.088,0.2],[-8.567,6.966],[-40.986,1.883],[-12.438,-5.561],[0.461,-13.625],[-4.541,-13.02]],"o":[[-0.769,10.327],[-0.572,6.498],[0,0],[0,0],[-6.042,-19.463],[-43.236,25.306],[0,0],[-3.585,13.57],[0,0],[0,0],[1.41,-11.634],[0,0],[-5.263,-9.626],[31.747,-25.898],[13.66,-0.65],[12.444,5.63],[13.711,-0.101],[8.968,25.565]],"v":[[146.555,-35.053],[130.378,-21.925],[130.876,-3.954],[116.784,-58.023],[100.498,-74.382],[90.807,-104.731],[-49.538,-100.509],[-55.67,-67.438],[-72.45,-49.727],[-82.564,-1.092],[-99.506,-115.859],[-82.957,-142.002],[-83.12,-142.265],[-71.543,-170.439],[43.438,-208.12],[83.697,-202.936],[106.04,-171.411],[136.1,-147.052]],"c":true},"ix":2},"nm":"Path 1","mn":"ADBE Vector Shape - Group","hd":false},{"ty":"fl","c":{"a":0,"k":[0,0.827450990677,0.509803950787,1],"ix":4},"o":{"a":0,"k":100,"ix":5},"r":1,"bm":0,"nm":"Fill 1","mn":"ADBE Vector Graphic - Fill","hd":false},{"ty":"tr","p":{"a":0,"k":[0,0],"ix":2},"a":{"a":0,"k":[0,0],"ix":1},"s":{"a":0,"k":[100,100],"ix":3},"r":{"a":0,"k":0,"ix":6},"o":{"a":0,"k":100,"ix":7},"sk":{"a":0,"k":0,"ix":4},"sa":{"a":0,"k":0,"ix":5},"nm":"Transform"}],"nm":"Group 1","np":2,"cix":2,"bm":0,"ix":1,"mn":"ADBE Vector Group","hd":false},{"ty":"gr","it":[{"ind":0,"ty":"sh","ix":1,"ks":{"a":0,"k":{"i":[[-0.033,-70.193],[71.078,-0.947],[7.813,2.043],[1.589,64.574],[-36.987,20.982],[-24.086,0.307]],"o":[[0.029,73.866],[-8.926,0.139],[-54.64,-13.752],[-1.459,-60.22],[15.072,-8.543],[83.533,-1.139]],"v":[[131.536,-23.627],[25.892,122.323],[0.811,119.397],[-83.704,-20.735],[-36.299,-146.216],[22.031,-159.764]],"c":true},"ix":2},"nm":"Path 1","mn":"ADBE Vector Shape - Group","hd":false},{"ty":"st","c":{"a":0,"k":[0,0.827450990677,0.509803950787,1],"ix":3},"o":{"a":0,"k":100,"ix":4},"w":{"a":0,"k":7.393,"ix":5},"lc":1,"lj":1,"ml":10,"bm":0,"nm":"Stroke 1","mn":"ADBE Vector Graphic - Stroke","hd":false},{"ty":"tr","p":{"a":0,"k":[0,0],"ix":2},"a":{"a":0,"k":[0,0],"ix":1},"s":{"a":0,"k":[100,100],"ix":3},"r":{"a":0,"k":0,"ix":6},"o":{"a":0,"k":100,"ix":7},"sk":{"a":0,"k":0,"ix":4},"sa":{"a":0,"k":0,"ix":5},"nm":"Transform"}],"nm":"Group 2","np":2,"cix":2,"bm":0,"ix":2,"mn":"ADBE Vector Group","hd":false},{"ty":"tr","p":{"a":0,"k":[0,0],"ix":2},"a":{"a":0,"k":[0,0],"ix":1},"s":{"a":0,"k":[100,100],"ix":3},"r":{"a":0,"k":0,"ix":6},"o":{"a":0,"k":100,"ix":7},"sk":{"a":0,"k":0,"ix":4},"sa":{"a":0,"k":0,"ix":5},"nm":"Transform"}],"nm":"Group 10","np":2,"cix":2,"bm":0,"ix":10,"mn":"ADBE Vector Group","hd":false},{"ty":"gr","it":[{"ty":"gr","it":[{"ind":0,"ty":"sh","ix":1,"ks":{"a":0,"k":{"i":[[0,0],[0,0],[0,0],[-1.825,-0.629],[23.967,-14.802],[12.175,15.258],[-2.045,0.503],[0,0],[0,0],[0,0]],"o":[[0,0],[0,0],[1.825,0.566],[-20.512,25.608],[-32.436,-19.379],[2.139,-0.629],[0,0],[0,0],[0,0],[0,0]],"v":[[86.835,98.623],[87.521,138.19],[87.772,157.287],[93.247,159.049],[25.576,218.917],[-44.801,155.179],[-38.572,153.48],[-39.48,96.084],[-5.334,117.936],[41.113,122.629]],"c":true},"ix":2},"nm":"Path 1","mn":"ADBE Vector Shape - Group","hd":false},{"ty":"fl","c":{"a":0,"k":[0,0.827450990677,0.509803950787,1],"ix":4},"o":{"a":0,"k":100,"ix":5},"r":1,"bm":0,"nm":"Fill 1","mn":"ADBE Vector Graphic - Fill","hd":false},{"ty":"tr","p":{"a":0,"k":[0,0],"ix":2},"a":{"a":0,"k":[0,0],"ix":1},"s":{"a":0,"k":[100,100],"ix":3},"r":{"a":0,"k":0,"ix":6},"o":{"a":0,"k":100,"ix":7},"sk":{"a":0,"k":0,"ix":4},"sa":{"a":0,"k":0,"ix":5},"nm":"Transform"}],"nm":"Group 1","np":2,"cix":2,"bm":0,"ix":1,"mn":"ADBE Vector Group","hd":false},{"ty":"gr","it":[{"ind":0,"ty":"sh","ix":1,"ks":{"a":0,"k":{"i":[[0,0],[25.766,9.91],[15.29,8.085],[1.321,5.222],[-2.422,6.261],[3.933,83.935],[2.139,45.24],[-11.389,24.948],[-56.156,22.494],[-23.375,2.108]],"o":[[-27.874,-4.75],[-15.951,-6.135],[-4.971,-2.643],[-1.668,-6.512],[28.408,-73.805],[-2.045,-43.698],[-1.227,-25.923],[8.494,-18.656],[21.676,-8.652],[0,0]],"v":[[-86.925,808.469],[-167.274,786.416],[-214.118,765.086],[-223.21,751.369],[-219.781,731.99],[-198.797,490.848],[-205.089,357.425],[-199.112,262.51],[-68.489,164.7],[-38.572,153.48]],"c":false},"ix":2},"nm":"Path 1","mn":"ADBE Vector Shape - Group","hd":false},{"ty":"st","c":{"a":0,"k":[0,0.827450990677,0.509803950787,1],"ix":3},"o":{"a":0,"k":100,"ix":4},"w":{"a":0,"k":11.425,"ix":5},"lc":2,"lj":2,"bm":0,"nm":"Stroke 1","mn":"ADBE Vector Graphic - Stroke","hd":false},{"ty":"fl","c":{"a":0,"k":[0,0.215686276555,0.698039233685,1],"ix":4},"o":{"a":0,"k":100,"ix":5},"r":1,"bm":0,"nm":"Fill 1","mn":"ADBE Vector Graphic - Fill","hd":false},{"ty":"tr","p":{"a":0,"k":[0,0],"ix":2},"a":{"a":0,"k":[0,0],"ix":1},"s":{"a":0,"k":[100,100],"ix":3},"r":{"a":0,"k":0,"ix":6},"o":{"a":0,"k":100,"ix":7},"sk":{"a":0,"k":0,"ix":4},"sa":{"a":0,"k":0,"ix":5},"nm":"Transform"}],"nm":"Group 2","np":3,"cix":2,"bm":0,"ix":2,"mn":"ADBE Vector Group","hd":false},{"ty":"gr","it":[{"ind":0,"ty":"sh","ix":1,"ks":{"a":0,"k":{"i":[[1.227,-3.523],[2.139,-2.045],[19.379,-7.897],[62.197,-3.083],[34.166,5.915],[25.766,9.91],[15.29,8.085],[1.321,5.222],[-2.422,6.261],[3.933,83.935],[2.139,45.24],[-11.389,24.948],[-56.156,22.494],[-23.375,2.108],[-12.773,0.032],[-3.618,-0.252],[-4.53,-0.629],[-7.141,-1.667],[-14.88,-6.198],[-9.878,-20.827],[-0.283,-12.553],[2.423,-56.786],[2.391,-43.478],[-19.851,-57.541]],"o":[[-0.912,2.643],[-15.352,14.629],[-58.61,23.909],[-38.004,1.919],[-27.874,-4.75],[-15.951,-6.135],[-4.971,-2.643],[-1.668,-6.512],[28.408,-73.805],[-2.045,-43.698],[-1.227,-25.923],[8.494,-18.656],[21.676,-8.652],[13.402,-1.258],[3.523,-0.031],[4.436,0.283],[7.016,0.944],[15.101,3.65],[66.066,27.339],[1.322,2.831],[0.818,27.37],[-1.699,38.853],[-3.587,64.965],[1.164,3.398]],"v":[[272.728,749.135],[267.474,756.025],[214.936,789.247],[21.172,814.51],[-86.925,808.469],[-167.274,786.416],[-214.118,765.086],[-223.21,751.369],[-219.781,731.99],[-198.797,490.848],[-205.089,357.425],[-199.112,262.51],[-68.489,164.7],[-13.685,151.707],[25.703,149.725],[36.462,150.071],[49.896,151.455],[71.1,155.482],[116.339,170.489],[251.964,265.876],[254.418,289.408],[251.429,421.258],[245.043,546.689],[271.564,738.534]],"c":true},"ix":2},"nm":"Path 1","mn":"ADBE Vector Shape - Group","hd":false},{"ty":"st","c":{"a":0,"k":[0,0.827450990677,0.509803950787,1],"ix":3},"o":{"a":0,"k":100,"ix":4},"w":{"a":0,"k":11.425,"ix":5},"lc":2,"lj":2,"bm":0,"nm":"Stroke 1","mn":"ADBE Vector Graphic - Stroke","hd":false},{"ty":"fl","c":{"a":0,"k":[0,0.215686276555,0.698039233685,1],"ix":4},"o":{"a":0,"k":100,"ix":5},"r":1,"bm":0,"nm":"Fill 1","mn":"ADBE Vector Graphic - Fill","hd":false},{"ty":"tr","p":{"a":0,"k":[0,0],"ix":2},"a":{"a":0,"k":[0,0],"ix":1},"s":{"a":0,"k":[100,100],"ix":3},"r":{"a":0,"k":0,"ix":6},"o":{"a":0,"k":100,"ix":7},"sk":{"a":0,"k":0,"ix":4},"sa":{"a":0,"k":0,"ix":5},"nm":"Transform"}],"nm":"Group 3","np":3,"cix":2,"bm":0,"ix":3,"mn":"ADBE Vector Group","hd":false},{"ty":"tr","p":{"a":0,"k":[0,0],"ix":2},"a":{"a":0,"k":[0,0],"ix":1},"s":{"a":0,"k":[100,100],"ix":3},"r":{"a":0,"k":0,"ix":6},"o":{"a":0,"k":100,"ix":7},"sk":{"a":0,"k":0,"ix":4},"sa":{"a":0,"k":0,"ix":5},"nm":"Transform"}],"nm":"Group 11","np":3,"cix":2,"bm":0,"ix":11,"mn":"ADBE Vector Group","hd":false},{"ty":"gr","it":[{"ind":0,"ty":"sh","ix":1,"ks":{"a":0,"k":{"i":[[-0.952,-20.751],[1.043,0.184],[0,0],[0,0],[29.991,16.362],[5.065,2.855],[-49.208,69.836]],"o":[[-1.074,-0.184],[0,0],[0,0],[-34.074,-7.03],[-4.574,-2.517],[35.087,-129.91],[0,0]],"v":[[-182.579,583.954],[-185.772,583.371],[-186.877,583.156],[-193.814,581.775],[-279.029,549.297],[-293.426,541.285],[-192.095,252.364]],"c":true},"ix":2},"nm":"Path 1","mn":"ADBE Vector Shape - Group","hd":false},{"ty":"st","c":{"a":0,"k":[0,0.827450990677,0.509803950787,1],"ix":3},"o":{"a":0,"k":100,"ix":4},"w":{"a":0,"k":11.425,"ix":5},"lc":2,"lj":2,"bm":0,"nm":"Stroke 1","mn":"ADBE Vector Graphic - Stroke","hd":false},{"ty":"fl","c":{"a":0,"k":[0,0.215686276555,0.698039233685,1],"ix":4},"o":{"a":0,"k":100,"ix":5},"r":1,"bm":0,"nm":"Fill 1","mn":"ADBE Vector Graphic - Fill","hd":false},{"ty":"tr","p":{"a":0,"k":[0,0],"ix":2},"a":{"a":0,"k":[0,0],"ix":1},"s":{"a":0,"k":[100,100],"ix":3},"r":{"a":0,"k":0,"ix":6},"o":{"a":0,"k":100,"ix":7},"sk":{"a":0,"k":0,"ix":4},"sa":{"a":0,"k":0,"ix":5},"nm":"Transform"}],"nm":"Group 12","np":3,"cix":2,"bm":0,"ix":12,"mn":"ADBE Vector Group","hd":false},{"ty":"tr","p":{"a":0,"k":[0,0],"ix":2},"a":{"a":0,"k":[0,0],"ix":1},"s":{"a":0,"k":[100,100],"ix":3},"r":{"a":0,"k":0,"ix":6},"o":{"a":0,"k":100,"ix":7},"sk":{"a":0,"k":0,"ix":4},"sa":{"a":0,"k":0,"ix":5},"nm":"Transform"}],"nm":"Group 1","np":12,"cix":2,"bm":0,"ix":1,"mn":"ADBE Vector Group","hd":false},{"ty":"gr","it":[{"ind":0,"ty":"sh","ix":1,"ks":{"a":0,"k":{"i":[[49.251,66.552],[0.733,-25.79],[0.73,-15.05],[-15.53,5.632],[-22.435,12.028]],"o":[[0,0],[-2.349,82.669],[21.545,-3.68],[18.047,-6.545],[-35.183,-123.76]],"v":[[251.963,265.897],[250.758,308.45],[242.654,581.77],[296.115,568.269],[353.486,541.195]],"c":true},"ix":2},"nm":"Path 1","mn":"ADBE Vector Shape - Group","hd":false},{"ty":"st","c":{"a":0,"k":[0,0.827450990677,0.509803950787,1],"ix":3},"o":{"a":0,"k":100,"ix":4},"w":{"a":0,"k":11.425,"ix":5},"lc":2,"lj":2,"bm":0,"nm":"Stroke 1","mn":"ADBE Vector Graphic - Stroke","hd":false},{"ty":"fl","c":{"a":0,"k":[0,0.215686276555,0.698039233685,1],"ix":4},"o":{"a":0,"k":100,"ix":5},"r":1,"bm":0,"nm":"Fill 1","mn":"ADBE Vector Graphic - Fill","hd":false},{"ty":"tr","p":{"a":0,"k":[0,0],"ix":2},"a":{"a":0,"k":[0,0],"ix":1},"s":{"a":0,"k":[100,100],"ix":3},"r":{"a":0,"k":0,"ix":6},"o":{"a":0,"k":100,"ix":7},"sk":{"a":0,"k":0,"ix":4},"sa":{"a":0,"k":0,"ix":5},"nm":"Transform"}],"nm":"Group 2","np":3,"cix":2,"bm":0,"ix":2,"mn":"ADBE Vector Group","hd":false},{"ty":"tr","p":{"a":0,"k":[0,0],"ix":2},"a":{"a":0,"k":[0,0],"ix":1},"s":{"a":0,"k":[100,100],"ix":3},"r":{"a":0,"k":0,"ix":6},"o":{"a":0,"k":100,"ix":7},"sk":{"a":0,"k":0,"ix":4},"sa":{"a":0,"k":0,"ix":5},"nm":"Transform"}],"nm":"Group 4","np":2,"cix":2,"bm":0,"ix":4,"mn":"ADBE Vector Group","hd":false},{"ty":"tr","p":{"a":0,"k":[0,0],"ix":2},"a":{"a":0,"k":[0,0],"ix":1},"s":{"a":0,"k":[100,100],"ix":3},"r":{"a":0,"k":0,"ix":6},"o":{"a":0,"k":100,"ix":7},"sk":{"a":0,"k":0,"ix":4},"sa":{"a":0,"k":0,"ix":5},"nm":"Transform"}],"nm":"Group 1","np":4,"cix":2,"bm":0,"ix":1,"mn":"ADBE Vector Group","hd":false},{"ty":"tr","p":{"a":0,"k":[0,0],"ix":2},"a":{"a":0,"k":[0,0],"ix":1},"s":{"a":0,"k":[100,100],"ix":3},"r":{"a":0,"k":0,"ix":6},"o":{"a":0,"k":100,"ix":7},"sk":{"a":0,"k":0,"ix":4},"sa":{"a":0,"k":0,"ix":5},"nm":"Transform"}],"nm":"Group 1","np":1,"cix":2,"bm":0,"ix":1,"mn":"ADBE Vector Group","hd":false}],"ip":0,"op":84,"st":0,"bm":0},{"ddd":0,"ind":6,"ty":4,"nm":"fondo caripe","parent":5,"sr":1,"ks":{"o":{"a":0,"k":100,"ix":11},"r":{"a":0,"k":0,"ix":10},"p":{"a":0,"k":[0,2.338,0],"ix":2,"l":2},"a":{"a":0,"k":[0,0,0],"ix":1,"l":2},"s":{"a":0,"k":[100,100,100],"ix":6,"l":2}},"ao":0,"sy":[{"c":{"a":0,"k":[0,0,0,1],"ix":2},"o":{"a":0,"k":75,"ix":3},"a":{"a":0,"k":120,"ix":5},"s":{"a":0,"k":5,"ix":8},"d":{"a":0,"k":5,"ix":6},"ch":{"a":0,"k":0,"ix":7},"bm":{"a":0,"k":5,"ix":1},"no":{"a":0,"k":0,"ix":9},"lc":{"a":0,"k":1,"ix":10},"ty":1,"nm":"Drop Shadow"},{"c":{"a":0,"k":[0,0,0,1],"ix":2},"o":{"a":0,"k":75,"ix":3},"a":{"a":0,"k":120,"ix":5},"s":{"a":0,"k":5,"ix":8},"d":{"a":0,"k":5,"ix":6},"ch":{"a":0,"k":0,"ix":7},"bm":{"a":0,"k":5,"ix":1},"no":{"a":0,"k":0,"ix":9},"ty":2,"nm":"Inner Shadow"},{"c":{"a":0,"k":[1,1,0.745098039216,1],"ix":5},"o":{"a":0,"k":75,"ix":2},"s":{"a":0,"k":5,"ix":10},"r":{"a":0,"k":50,"ix":11},"ch":{"a":0,"k":0,"ix":9},"bm":{"a":0,"k":11,"ix":1},"no":{"a":0,"k":0,"ix":3},"j":{"a":0,"k":0,"ix":12},"ty":3,"nm":"Outer Glow"},{"c":{"a":0,"k":[1,1,0.745098039216,1],"ix":5},"o":{"a":0,"k":75,"ix":2},"s":{"a":0,"k":5,"ix":11},"r":{"a":0,"k":50,"ix":12},"sr":{"a":0,"k":1,"ix":9},"ch":{"a":0,"k":0,"ix":10},"bm":{"a":0,"k":11,"ix":1},"no":{"a":0,"k":0,"ix":3},"j":{"a":0,"k":0,"ix":13},"ty":4,"nm":"Inner Glow"},{"bs":{"a":0,"k":2,"ix":1},"bt":{"a":0,"k":1,"ix":2},"sr":{"a":0,"k":100,"ix":3},"bd":{"a":0,"k":1,"ix":4},"s":{"a":0,"k":5,"ix":5},"so":{"a":0,"k":75,"ix":15},"ga":{"a":0,"k":0,"ix":7},"a":{"a":0,"k":120,"ix":8},"ll":{"a":0,"k":30,"ix":9},"hm":{"a":0,"k":11,"ix":10},"hc":{"a":0,"k":[1,1,1,1],"ix":11},"ho":{"a":0,"k":75,"ix":12},"sm":{"a":0,"k":5,"ix":13},"sc":{"a":0,"k":[0,0,0,1],"ix":14},"ty":5,"nm":"Bevel and Emboss"},{"bm":{"a":0,"k":5,"ix":1},"c":{"a":0,"k":[0,0,0,1],"ix":2},"o":{"a":0,"k":50,"ix":3},"a":{"a":0,"k":19,"ix":4},"d":{"a":0,"k":11,"ix":5},"s":{"a":0,"k":14,"ix":6},"in":{"a":0,"k":1,"ix":7},"ty":6,"nm":"Satin"},{"bm":{"a":0,"k":1,"ix":1},"c":{"a":0,"k":[1,0,0,1],"ix":2},"so":{"a":0,"k":100,"ix":3},"ty":7,"nm":"Color Overlay"},{"bm":{"a":0,"k":1,"ix":1},"o":{"a":0,"k":100,"ix":2},"gf":{"a":0,"ix":3},"gs":{"a":0,"k":100,"ix":4},"a":{"a":0,"k":90,"ix":5},"gt":{"a":0,"k":1,"ix":6},"re":{"a":0,"k":0,"ix":7},"al":{"a":0,"k":1,"ix":8},"s":{"a":0,"k":100,"ix":9},"of":{"a":0,"k":[0,0],"ix":10},"ty":8,"nm":"Gradient Overlay"},{"c":{"a":0,"k":[1,0,0,1],"ix":2},"s":{"a":0,"k":3,"ix":3},"ty":0,"nm":"Stroke"}],"shapes":[{"ty":"gr","it":[{"ind":0,"ty":"sh","ix":1,"ks":{"a":0,"k":{"i":[[0,0],[0,0],[11,80],[0,0],[0,0],[7.122,-38.633],[48.497,-28.282]],"o":[[0,0],[0,0],[-11,-80],[0,0],[0,0],[-7.122,38.633],[-48.497,28.282]],"v":[[26,133],[-34.592,101.298],[-86,-15],[-35,-132],[96,-126],[137,-7],[64.497,113.718]],"c":true},"ix":2},"nm":"Path 1","mn":"ADBE Vector Shape - Group","hd":false},{"ty":"fl","c":{"a":0,"k":[0,0.215686276555,0.698039233685,1],"ix":4},"o":{"a":0,"k":100,"ix":5},"r":1,"bm":0,"nm":"Fill 1","mn":"ADBE Vector Graphic - Fill","hd":false},{"ty":"tr","p":{"a":0,"k":[0,0],"ix":2},"a":{"a":0,"k":[0,0],"ix":1},"s":{"a":0,"k":[100,100],"ix":3},"r":{"a":0,"k":0,"ix":6},"o":{"a":0,"k":100,"ix":7},"sk":{"a":0,"k":0,"ix":4},"sa":{"a":0,"k":0,"ix":5},"nm":"Transform"}],"nm":"Group 1","np":2,"cix":2,"bm":0,"ix":1,"mn":"ADBE Vector Group","hd":false}],"ip":0,"op":84,"st":0,"bm":0},{"ddd":0,"ind":8,"ty":4,"nm":"telefono","parent":5,"sr":1,"ks":{"o":{"a":0,"k":100,"ix":11},"r":{"a":0,"k":0,"ix":10},"p":{"a":1,"k":[{"i":{"x":0.667,"y":1},"o":{"x":0.333,"y":0},"t":23,"s":[22,12,0],"to":[0,0,0],"ti":[0,0,0]},{"i":{"x":0.667,"y":1},"o":{"x":0.333,"y":0},"t":28,"s":[12,54,0],"to":[0,0,0],"ti":[0,0,0]},{"i":{"x":0.667,"y":1},"o":{"x":0.333,"y":0},"t":33,"s":[22,12,0],"to":[0,0,0],"ti":[0,0,0]},{"t":44,"s":[-6,-10,0]}],"ix":2,"l":2},"a":{"a":0,"k":[22,12,0],"ix":1,"l":2},"s":{"a":1,"k":[{"i":{"x":[0.667,0.667,0.667],"y":[1,1,1]},"o":{"x":[0.333,0.333,0.333],"y":[0,0,0]},"t":23,"s":[30,30,100]},{"t":33,"s":[94,94,100]}],"ix":6,"l":2}},"ao":0,"sy":[{"c":{"a":0,"k":[0,0,0,1],"ix":2},"o":{"a":0,"k":75,"ix":3},"a":{"a":0,"k":120,"ix":5},"s":{"a":0,"k":5,"ix":8},"d":{"a":0,"k":5,"ix":6},"ch":{"a":0,"k":0,"ix":7},"bm":{"a":0,"k":5,"ix":1},"no":{"a":0,"k":0,"ix":9},"lc":{"a":0,"k":1,"ix":10},"ty":1,"nm":"Drop Shadow"},{"c":{"a":0,"k":[0,0,0,1],"ix":2},"o":{"a":0,"k":75,"ix":3},"a":{"a":0,"k":120,"ix":5},"s":{"a":0,"k":5,"ix":8},"d":{"a":0,"k":5,"ix":6},"ch":{"a":0,"k":0,"ix":7},"bm":{"a":0,"k":5,"ix":1},"no":{"a":0,"k":0,"ix":9},"ty":2,"nm":"Inner Shadow"},{"c":{"a":0,"k":[1,1,0.745098039216,1],"ix":5},"o":{"a":0,"k":75,"ix":2},"s":{"a":0,"k":5,"ix":10},"r":{"a":0,"k":50,"ix":11},"ch":{"a":0,"k":0,"ix":9},"bm":{"a":0,"k":11,"ix":1},"no":{"a":0,"k":0,"ix":3},"j":{"a":0,"k":0,"ix":12},"ty":3,"nm":"Outer Glow"},{"c":{"a":0,"k":[1,1,0.745098039216,1],"ix":5},"o":{"a":0,"k":75,"ix":2},"s":{"a":0,"k":5,"ix":11},"r":{"a":0,"k":50,"ix":12},"sr":{"a":0,"k":1,"ix":9},"ch":{"a":0,"k":0,"ix":10},"bm":{"a":0,"k":11,"ix":1},"no":{"a":0,"k":0,"ix":3},"j":{"a":0,"k":0,"ix":13},"ty":4,"nm":"Inner Glow"},{"bs":{"a":0,"k":2,"ix":1},"bt":{"a":0,"k":1,"ix":2},"sr":{"a":0,"k":100,"ix":3},"bd":{"a":0,"k":1,"ix":4},"s":{"a":0,"k":5,"ix":5},"so":{"a":0,"k":75,"ix":15},"ga":{"a":0,"k":0,"ix":7},"a":{"a":0,"k":120,"ix":8},"ll":{"a":0,"k":30,"ix":9},"hm":{"a":0,"k":11,"ix":10},"hc":{"a":0,"k":[1,1,1,1],"ix":11},"ho":{"a":0,"k":75,"ix":12},"sm":{"a":0,"k":5,"ix":13},"sc":{"a":0,"k":[0,0,0,1],"ix":14},"ty":5,"nm":"Bevel and Emboss"},{"bm":{"a":0,"k":5,"ix":1},"c":{"a":0,"k":[0,0,0,1],"ix":2},"o":{"a":0,"k":50,"ix":3},"a":{"a":0,"k":19,"ix":4},"d":{"a":0,"k":11,"ix":5},"s":{"a":0,"k":14,"ix":6},"in":{"a":0,"k":1,"ix":7},"ty":6,"nm":"Satin"},{"bm":{"a":0,"k":1,"ix":1},"c":{"a":0,"k":[1,0,0,1],"ix":2},"so":{"a":0,"k":100,"ix":3},"ty":7,"nm":"Color Overlay"},{"bm":{"a":0,"k":1,"ix":1},"o":{"a":0,"k":100,"ix":2},"gf":{"a":0,"ix":3},"gs":{"a":0,"k":100,"ix":4},"a":{"a":0,"k":90,"ix":5},"gt":{"a":0,"k":1,"ix":6},"re":{"a":0,"k":0,"ix":7},"al":{"a":0,"k":1,"ix":8},"s":{"a":0,"k":100,"ix":9},"of":{"a":0,"k":[0,0],"ix":10},"ty":8,"nm":"Gradient Overlay"},{"c":{"a":0,"k":[1,0,0,1],"ix":2},"s":{"a":0,"k":3,"ix":3},"ty":0,"nm":"Stroke"}],"shapes":[{"ty":"gr","it":[{"ind":0,"ty":"sh","ix":1,"ks":{"a":0,"k":{"i":[[0,0]],"o":[[0,0]],"v":[[-715.234,113.064]],"c":false},"ix":2},"nm":"Path 1","mn":"ADBE Vector Shape - Group","hd":false},{"ty":"st","c":{"a":0,"k":[1,1,1,1],"ix":3},"o":{"a":0,"k":100,"ix":4},"w":{"a":0,"k":2,"ix":5},"lc":1,"lj":1,"ml":4,"bm":0,"nm":"Stroke 1","mn":"ADBE Vector Graphic - Stroke","hd":false},{"ty":"fl","c":{"a":0,"k":[1,0,0,1],"ix":4},"o":{"a":0,"k":100,"ix":5},"r":1,"bm":0,"nm":"Fill 1","mn":"ADBE Vector Graphic - Fill","hd":false},{"ty":"tr","p":{"a":0,"k":[0,0],"ix":2},"a":{"a":0,"k":[0,0],"ix":1},"s":{"a":0,"k":[100,100],"ix":3},"r":{"a":0,"k":0,"ix":6},"o":{"a":0,"k":100,"ix":7},"sk":{"a":0,"k":0,"ix":4},"sa":{"a":0,"k":0,"ix":5},"nm":"Transform"}],"nm":"Shape 1","np":3,"cix":2,"bm":0,"ix":1,"mn":"ADBE Vector Group","hd":false},{"ty":"gr","it":[{"ind":0,"ty":"sh","ix":1,"ks":{"a":0,"k":{"i":[[-6.141,0.639],[-14.249,14.249],[-0.992,9.542],[2.844,2.723],[1.086,-1.606],[0,0],[-1.519,-0.918],[0,0],[0.932,-2.814],[4.681,-1.55],[1.534,2.536],[0,0],[1.47,-0.994],[0,0],[-1.34,-1.4]],"o":[[9.542,-0.993],[14.249,-14.249],[0.639,-6.141],[-1.4,-1.34],[0,0],[-0.994,1.47],[0,0],[2.536,1.534],[-1.55,4.681],[-2.814,0.932],[0,0],[-0.918,-1.519],[0,0],[-1.606,1.086],[2.723,2.844]],"v":[[267.78,160.352],[307.288,138.578],[329.061,99.07],[322.979,85.291],[318.237,85.77],[304.692,105.802],[305.656,110.194],[308.477,111.899],[310.357,119.274],[287.983,141.647],[280.609,139.767],[278.904,136.947],[274.512,135.982],[254.48,149.527],[254.001,154.27]],"c":true},"ix":2},"nm":"Path 1","mn":"ADBE Vector Shape - Group","hd":false},{"ty":"fl","c":{"a":0,"k":[0,0.215686276555,0.698039233685,1],"ix":4},"o":{"a":0,"k":100,"ix":5},"r":1,"bm":0,"nm":"Fill 1","mn":"ADBE Vector Graphic - Fill","hd":false},{"ty":"tr","p":{"a":0,"k":[0,0],"ix":2},"a":{"a":0,"k":[0,0],"ix":1},"s":{"a":0,"k":[100,100],"ix":3},"r":{"a":0,"k":0,"ix":6},"o":{"a":0,"k":100,"ix":7},"sk":{"a":0,"k":0,"ix":4},"sa":{"a":0,"k":0,"ix":5},"nm":"Transform"}],"nm":"Group 1","np":2,"cix":2,"bm":0,"ix":2,"mn":"ADBE Vector Group","hd":false},{"ty":"gr","it":[{"ind":0,"ty":"sh","ix":1,"ks":{"a":0,"k":{"i":[[0,-35.794],[35.794,0],[0,35.794],[-35.794,0]],"o":[[0,35.794],[-35.794,0],[0,-35.794],[35.794,0]],"v":[[355.937,124.02],[291.126,188.831],[226.315,124.02],[291.126,59.209]],"c":true},"ix":2},"nm":"Path 1","mn":"ADBE Vector Shape - Group","hd":false},{"ty":"fl","c":{"a":0,"k":[1,1,1,1],"ix":4},"o":{"a":0,"k":100,"ix":5},"r":1,"bm":0,"nm":"Fill 1","mn":"ADBE Vector Graphic - Fill","hd":false},{"ty":"tr","p":{"a":0,"k":[0,0],"ix":2},"a":{"a":0,"k":[0,0],"ix":1},"s":{"a":0,"k":[100,100],"ix":3},"r":{"a":0,"k":0,"ix":6},"o":{"a":0,"k":100,"ix":7},"sk":{"a":0,"k":0,"ix":4},"sa":{"a":0,"k":0,"ix":5},"nm":"Transform"}],"nm":"Group 2","np":2,"cix":2,"bm":0,"ix":3,"mn":"ADBE Vector Group","hd":false}],"ip":0,"op":84,"st":0,"bm":0},{"ddd":0,"ind":9,"ty":4,"nm":"sobre","parent":5,"sr":1,"ks":{"o":{"a":0,"k":100,"ix":11},"r":{"a":0,"k":0,"ix":10},"p":{"a":1,"k":[{"i":{"x":0.667,"y":1},"o":{"x":0.333,"y":0},"t":25,"s":[0,0,0],"to":[0,0,0],"ti":[0,0,0]},{"i":{"x":0.667,"y":1},"o":{"x":0.333,"y":0},"t":36.813,"s":[0,39,0],"to":[0,0,0],"ti":[0,0,0]},{"t":46,"s":[0,0,0]}],"ix":2,"l":2},"a":{"a":0,"k":[0,0,0],"ix":1,"l":2},"s":{"a":1,"k":[{"i":{"x":[0.667,0.667,0.667],"y":[1,1,1]},"o":{"x":[0.333,0.333,0.333],"y":[0,0,0]},"t":29,"s":[28,28,100]},{"t":40,"s":[100,100,100]}],"ix":6,"l":2}},"ao":0,"sy":[{"c":{"a":0,"k":[0,0,0,1],"ix":2},"o":{"a":0,"k":75,"ix":3},"a":{"a":0,"k":120,"ix":5},"s":{"a":0,"k":5,"ix":8},"d":{"a":0,"k":5,"ix":6},"ch":{"a":0,"k":0,"ix":7},"bm":{"a":0,"k":5,"ix":1},"no":{"a":0,"k":0,"ix":9},"lc":{"a":0,"k":1,"ix":10},"ty":1,"nm":"Drop Shadow"},{"c":{"a":0,"k":[0,0,0,1],"ix":2},"o":{"a":0,"k":75,"ix":3},"a":{"a":0,"k":120,"ix":5},"s":{"a":0,"k":5,"ix":8},"d":{"a":0,"k":5,"ix":6},"ch":{"a":0,"k":0,"ix":7},"bm":{"a":0,"k":5,"ix":1},"no":{"a":0,"k":0,"ix":9},"ty":2,"nm":"Inner Shadow"},{"c":{"a":0,"k":[1,1,0.745098039216,1],"ix":5},"o":{"a":0,"k":75,"ix":2},"s":{"a":0,"k":5,"ix":10},"r":{"a":0,"k":50,"ix":11},"ch":{"a":0,"k":0,"ix":9},"bm":{"a":0,"k":11,"ix":1},"no":{"a":0,"k":0,"ix":3},"j":{"a":0,"k":0,"ix":12},"ty":3,"nm":"Outer Glow"},{"c":{"a":0,"k":[1,1,0.745098039216,1],"ix":5},"o":{"a":0,"k":75,"ix":2},"s":{"a":0,"k":5,"ix":11},"r":{"a":0,"k":50,"ix":12},"sr":{"a":0,"k":1,"ix":9},"ch":{"a":0,"k":0,"ix":10},"bm":{"a":0,"k":11,"ix":1},"no":{"a":0,"k":0,"ix":3},"j":{"a":0,"k":0,"ix":13},"ty":4,"nm":"Inner Glow"},{"bs":{"a":0,"k":2,"ix":1},"bt":{"a":0,"k":1,"ix":2},"sr":{"a":0,"k":100,"ix":3},"bd":{"a":0,"k":1,"ix":4},"s":{"a":0,"k":5,"ix":5},"so":{"a":0,"k":75,"ix":15},"ga":{"a":0,"k":0,"ix":7},"a":{"a":0,"k":120,"ix":8},"ll":{"a":0,"k":30,"ix":9},"hm":{"a":0,"k":11,"ix":10},"hc":{"a":0,"k":[1,1,1,1],"ix":11},"ho":{"a":0,"k":75,"ix":12},"sm":{"a":0,"k":5,"ix":13},"sc":{"a":0,"k":[0,0,0,1],"ix":14},"ty":5,"nm":"Bevel and Emboss"},{"bm":{"a":0,"k":5,"ix":1},"c":{"a":0,"k":[0,0,0,1],"ix":2},"o":{"a":0,"k":50,"ix":3},"a":{"a":0,"k":19,"ix":4},"d":{"a":0,"k":11,"ix":5},"s":{"a":0,"k":14,"ix":6},"in":{"a":0,"k":1,"ix":7},"ty":6,"nm":"Satin"},{"bm":{"a":0,"k":1,"ix":1},"c":{"a":0,"k":[1,0,0,1],"ix":2},"so":{"a":0,"k":100,"ix":3},"ty":7,"nm":"Color Overlay"},{"bm":{"a":0,"k":1,"ix":1},"o":{"a":0,"k":100,"ix":2},"gf":{"a":0,"ix":3},"gs":{"a":0,"k":100,"ix":4},"a":{"a":0,"k":90,"ix":5},"gt":{"a":0,"k":1,"ix":6},"re":{"a":0,"k":0,"ix":7},"al":{"a":0,"k":1,"ix":8},"s":{"a":0,"k":100,"ix":9},"of":{"a":0,"k":[0,0],"ix":10},"ty":8,"nm":"Gradient Overlay"},{"c":{"a":0,"k":[1,0,0,1],"ix":2},"s":{"a":0,"k":3,"ix":3},"ty":0,"nm":"Stroke"}],"shapes":[{"ty":"gr","it":[{"ty":"gr","it":[{"ind":0,"ty":"sh","ix":1,"ks":{"a":0,"k":{"i":[[0,0],[0,0],[0,0],[0,0],[0,0]],"o":[[0,0],[0,0],[0,0],[0,0],[0,0]],"v":[[327.716,-189.228],[327.716,-125.849],[232.496,-125.849],[232.496,-189.253],[280.119,-156.019]],"c":true},"ix":2},"nm":"Path 1","mn":"ADBE Vector Shape - Group","hd":false},{"ty":"fl","c":{"a":0,"k":[0,0.215686276555,0.698039233685,1],"ix":4},"o":{"a":0,"k":100,"ix":5},"r":1,"bm":0,"nm":"Fill 1","mn":"ADBE Vector Graphic - Fill","hd":false},{"ty":"tr","p":{"a":0,"k":[0,0],"ix":2},"a":{"a":0,"k":[0,0],"ix":1},"s":{"a":0,"k":[100,100],"ix":3},"r":{"a":0,"k":0,"ix":6},"o":{"a":0,"k":100,"ix":7},"sk":{"a":0,"k":0,"ix":4},"sa":{"a":0,"k":0,"ix":5},"nm":"Transform"}],"nm":"Group 1","np":2,"cix":2,"bm":0,"ix":1,"mn":"ADBE Vector Group","hd":false},{"ty":"gr","it":[{"ind":0,"ty":"sh","ix":1,"ks":{"a":0,"k":{"i":[[0,0],[0,0],[0,0]],"o":[[0,0],[0,0],[0,0]],"v":[[280.119,-162.174],[236.904,-192.344],[323.309,-192.344]],"c":true},"ix":2},"nm":"Path 1","mn":"ADBE Vector Shape - Group","hd":false},{"ty":"fl","c":{"a":0,"k":[0,0.215686276555,0.698039233685,1],"ix":4},"o":{"a":0,"k":100,"ix":5},"r":1,"bm":0,"nm":"Fill 1","mn":"ADBE Vector Graphic - Fill","hd":false},{"ty":"tr","p":{"a":0,"k":[0,0],"ix":2},"a":{"a":0,"k":[0,0],"ix":1},"s":{"a":0,"k":[100,100],"ix":3},"r":{"a":0,"k":0,"ix":6},"o":{"a":0,"k":100,"ix":7},"sk":{"a":0,"k":0,"ix":4},"sa":{"a":0,"k":0,"ix":5},"nm":"Transform"}],"nm":"Group 2","np":2,"cix":2,"bm":0,"ix":2,"mn":"ADBE Vector Group","hd":false},{"ty":"tr","p":{"a":0,"k":[0,0],"ix":2},"a":{"a":0,"k":[0,0],"ix":1},"s":{"a":0,"k":[100,100],"ix":3},"r":{"a":0,"k":0,"ix":6},"o":{"a":0,"k":100,"ix":7},"sk":{"a":0,"k":0,"ix":4},"sa":{"a":0,"k":0,"ix":5},"nm":"Transform"}],"nm":"Group 1","np":2,"cix":2,"bm":0,"ix":1,"mn":"ADBE Vector Group","hd":false},{"ty":"gr","it":[{"ty":"gr","it":[{"ind":0,"ty":"sh","ix":1,"ks":{"a":0,"k":{"i":[[0,-43.823],[43.823,0],[0,43.823],[-43.823,0]],"o":[[0,43.823],[-43.823,0],[0,-43.823],[43.823,0]],"v":[[357.556,-159.512],[278.208,-80.164],[198.859,-159.512],[278.208,-238.86]],"c":true},"ix":2},"nm":"Path 1","mn":"ADBE Vector Shape - Group","hd":false},{"ty":"fl","c":{"a":0,"k":[1,1,1,1],"ix":4},"o":{"a":0,"k":100,"ix":5},"r":1,"bm":0,"nm":"Fill 1","mn":"ADBE Vector Graphic - Fill","hd":false},{"ty":"tr","p":{"a":0,"k":[0,0],"ix":2},"a":{"a":0,"k":[0,0],"ix":1},"s":{"a":0,"k":[100,100],"ix":3},"r":{"a":0,"k":0,"ix":6},"o":{"a":0,"k":100,"ix":7},"sk":{"a":0,"k":0,"ix":4},"sa":{"a":0,"k":0,"ix":5},"nm":"Transform"}],"nm":"Group 1","np":2,"cix":2,"bm":0,"ix":1,"mn":"ADBE Vector Group","hd":false},{"ty":"tr","p":{"a":0,"k":[0,0],"ix":2},"a":{"a":0,"k":[0,0],"ix":1},"s":{"a":0,"k":[100,100],"ix":3},"r":{"a":0,"k":0,"ix":6},"o":{"a":0,"k":100,"ix":7},"sk":{"a":0,"k":0,"ix":4},"sa":{"a":0,"k":0,"ix":5},"nm":"Transform"}],"nm":"Group 2","np":1,"cix":2,"bm":0,"ix":2,"mn":"ADBE Vector Group","hd":false}],"ip":0,"op":84,"st":0,"bm":0},{"ddd":0,"ind":10,"ty":4,"nm":"24","parent":5,"sr":1,"ks":{"o":{"a":0,"k":100,"ix":11},"r":{"a":0,"k":0,"ix":10},"p":{"a":1,"k":[{"i":{"x":0.667,"y":1},"o":{"x":0.333,"y":0},"t":26,"s":[0,0,0],"to":[0,0,0],"ti":[0,0,0]},{"i":{"x":0.667,"y":1},"o":{"x":0.333,"y":0},"t":35.5,"s":[0,-42,0],"to":[0,0,0],"ti":[0,0,0]},{"t":45,"s":[0,0,0]}],"ix":2,"l":2},"a":{"a":0,"k":[0,0,0],"ix":1,"l":2},"s":{"a":1,"k":[{"i":{"x":[0.667,0.667,0.667],"y":[1,1,1]},"o":{"x":[0.333,0.333,0.333],"y":[0,0,0]},"t":26,"s":[4,4,100]},{"t":45,"s":[100,100,100]}],"ix":6,"l":2}},"ao":0,"sy":[{"c":{"a":0,"k":[0,0,0,1],"ix":2},"o":{"a":0,"k":75,"ix":3},"a":{"a":0,"k":120,"ix":5},"s":{"a":0,"k":5,"ix":8},"d":{"a":0,"k":5,"ix":6},"ch":{"a":0,"k":0,"ix":7},"bm":{"a":0,"k":5,"ix":1},"no":{"a":0,"k":0,"ix":9},"lc":{"a":0,"k":1,"ix":10},"ty":1,"nm":"Drop Shadow"},{"c":{"a":0,"k":[0,0,0,1],"ix":2},"o":{"a":0,"k":75,"ix":3},"a":{"a":0,"k":120,"ix":5},"s":{"a":0,"k":5,"ix":8},"d":{"a":0,"k":5,"ix":6},"ch":{"a":0,"k":0,"ix":7},"bm":{"a":0,"k":5,"ix":1},"no":{"a":0,"k":0,"ix":9},"ty":2,"nm":"Inner Shadow"},{"c":{"a":0,"k":[1,1,0.745098039216,1],"ix":5},"o":{"a":0,"k":75,"ix":2},"s":{"a":0,"k":5,"ix":10},"r":{"a":0,"k":50,"ix":11},"ch":{"a":0,"k":0,"ix":9},"bm":{"a":0,"k":11,"ix":1},"no":{"a":0,"k":0,"ix":3},"j":{"a":0,"k":0,"ix":12},"ty":3,"nm":"Outer Glow"},{"c":{"a":0,"k":[1,1,0.745098039216,1],"ix":5},"o":{"a":0,"k":75,"ix":2},"s":{"a":0,"k":5,"ix":11},"r":{"a":0,"k":50,"ix":12},"sr":{"a":0,"k":1,"ix":9},"ch":{"a":0,"k":0,"ix":10},"bm":{"a":0,"k":11,"ix":1},"no":{"a":0,"k":0,"ix":3},"j":{"a":0,"k":0,"ix":13},"ty":4,"nm":"Inner Glow"},{"bs":{"a":0,"k":2,"ix":1},"bt":{"a":0,"k":1,"ix":2},"sr":{"a":0,"k":100,"ix":3},"bd":{"a":0,"k":1,"ix":4},"s":{"a":0,"k":5,"ix":5},"so":{"a":0,"k":75,"ix":15},"ga":{"a":0,"k":0,"ix":7},"a":{"a":0,"k":120,"ix":8},"ll":{"a":0,"k":30,"ix":9},"hm":{"a":0,"k":11,"ix":10},"hc":{"a":0,"k":[1,1,1,1],"ix":11},"ho":{"a":0,"k":75,"ix":12},"sm":{"a":0,"k":5,"ix":13},"sc":{"a":0,"k":[0,0,0,1],"ix":14},"ty":5,"nm":"Bevel and Emboss"},{"bm":{"a":0,"k":5,"ix":1},"c":{"a":0,"k":[0,0,0,1],"ix":2},"o":{"a":0,"k":50,"ix":3},"a":{"a":0,"k":19,"ix":4},"d":{"a":0,"k":11,"ix":5},"s":{"a":0,"k":14,"ix":6},"in":{"a":0,"k":1,"ix":7},"ty":6,"nm":"Satin"},{"bm":{"a":0,"k":1,"ix":1},"c":{"a":0,"k":[1,0,0,1],"ix":2},"so":{"a":0,"k":100,"ix":3},"ty":7,"nm":"Color Overlay"},{"bm":{"a":0,"k":1,"ix":1},"o":{"a":0,"k":100,"ix":2},"gf":{"a":0,"ix":3},"gs":{"a":0,"k":100,"ix":4},"a":{"a":0,"k":90,"ix":5},"gt":{"a":0,"k":1,"ix":6},"re":{"a":0,"k":0,"ix":7},"al":{"a":0,"k":1,"ix":8},"s":{"a":0,"k":100,"ix":9},"of":{"a":0,"k":[0,0],"ix":10},"ty":8,"nm":"Gradient Overlay"},{"c":{"a":0,"k":[1,0,0,1],"ix":2},"s":{"a":0,"k":3,"ix":3},"ty":0,"nm":"Stroke"}],"shapes":[{"ty":"gr","it":[{"ty":"gr","it":[{"ty":"gr","it":[{"ty":"gr","it":[{"ty":"gr","it":[{"ind":0,"ty":"sh","ix":1,"ks":{"a":0,"k":{"i":[[0,0],[0,0],[-0.049,0.789],[-0.098,0.857],[0,0]],"o":[[0,0],[0,-0.682],[0.048,-0.789],[0,0],[0,0]],"v":[[-259.69,127.791],[-259.69,116.691],[-259.617,114.486],[-259.397,112.018],[-270.643,127.791]],"c":true},"ix":2},"nm":"Path 1","mn":"ADBE Vector Shape - Group","hd":false},{"ind":1,"ty":"sh","ix":2,"ks":{"a":0,"k":{"i":[[0,0],[0,0],[0.301,-0.331],[0.564,0],[0,0],[0,0],[0,0],[0,0],[0,0],[0.458,0.351],[0.117,0.526],[0,0],[0,0],[0,0],[0,0]],"o":[[0,0],[0,0.448],[-0.302,0.332],[0,0],[0,0],[0,0],[0,0],[0,0],[-0.565,0],[-0.458,-0.35],[0,0],[0,0],[0,0],[0,0],[0,0]],"v":[[-247.422,127.791],[-247.422,132.873],[-247.875,134.042],[-249.174,134.538],[-251.803,134.538],[-251.803,144.323],[-259.69,144.323],[-259.69,134.538],[-276.806,134.538],[-278.34,134.012],[-279.202,132.698],[-280.136,128.229],[-260.449,101.766],[-251.803,101.766],[-251.803,127.791]],"c":true},"ix":2},"nm":"Path 2","mn":"ADBE Vector Shape - Group","hd":false},{"ty":"fl","c":{"a":0,"k":[0,0.827450990677,0.509803950787,1],"ix":4},"o":{"a":0,"k":100,"ix":5},"r":1,"bm":0,"nm":"Fill 1","mn":"ADBE Vector Graphic - Fill","hd":false},{"ty":"tr","p":{"a":0,"k":[0,0],"ix":2},"a":{"a":0,"k":[0,0],"ix":1},"s":{"a":0,"k":[100,100],"ix":3},"r":{"a":0,"k":0,"ix":6},"o":{"a":0,"k":100,"ix":7},"sk":{"a":0,"k":0,"ix":4},"sa":{"a":0,"k":0,"ix":5},"nm":"Transform"}],"nm":"Group 1","np":3,"cix":2,"bm":0,"ix":1,"mn":"ADBE Vector Group","hd":false},{"ty":"gr","it":[{"ind":0,"ty":"sh","ix":1,"ks":{"a":0,"k":{"i":[[0,0],[-0.565,-0.535],[0,-0.876],[0,0],[0,0],[0,0],[-0.233,0.643],[-0.584,0.526],[0,0],[-0.779,0.955],[-0.506,0.925],[-0.253,0.925],[0,1.032],[0.808,0.905],[1.655,0],[0.925,-0.711],[0.351,-1.051],[0.662,-0.351],[1.227,0.195],[0,0],[-0.887,1.577],[-1.314,1.052],[-1.694,0.516],[-1.947,0],[-1.685,-0.613],[-1.188,-1.09],[-0.633,-1.509],[0,-1.811],[0.438,-1.324],[0.759,-1.198],[1.003,-1.119],[1.129,-1.148],[0,0],[-1.052,0.175],[-0.896,0]],"o":[[0.973,0],[0.564,0.536],[0,0],[0,0],[0,0],[0,-0.564],[0.234,-0.643],[0,0],[1.052,-1.052],[0.779,-0.954],[0.506,-0.925],[0.253,-0.925],[0,-1.694],[-0.809,-0.906],[-1.344,0],[-0.925,0.711],[-0.409,1.071],[-0.662,0.351],[0,0],[0.311,-2.122],[0.886,-1.577],[1.314,-1.051],[1.694,-0.516],[2.103,0],[1.684,0.613],[1.188,1.091],[0.632,1.509],[0,1.558],[-0.438,1.324],[-0.759,1.197],[-1.003,1.12],[0,0],[1.071,-0.331],[1.051,-0.175],[0,0]],"v":[[-285.364,136.145],[-283.056,136.948],[-282.209,139.065],[-282.209,144.323],[-312.12,144.323],[-312.12,141.402],[-311.769,139.591],[-310.542,137.839],[-298.274,125.483],[-295.529,122.475],[-293.601,119.656],[-292.462,116.881],[-292.082,113.946],[-293.294,110.046],[-296.989,108.688],[-300.392,109.754],[-302.305,112.397],[-303.912,114.53],[-306.745,114.764],[-311.535,113.917],[-309.739,108.367],[-306.438,104.423],[-301.925,102.072],[-296.463,101.298],[-290.782,102.218],[-286.474,104.774],[-283.743,108.673],[-282.793,113.654],[-283.451,117.977],[-285.247,121.759],[-287.891,125.235],[-291.089,128.638],[-299.414,137.167],[-296.229,136.408],[-293.309,136.145]],"c":true},"ix":2},"nm":"Path 1","mn":"ADBE Vector Shape - Group","hd":false},{"ty":"fl","c":{"a":0,"k":[0,0.827450990677,0.509803950787,1],"ix":4},"o":{"a":0,"k":100,"ix":5},"r":1,"bm":0,"nm":"Fill 1","mn":"ADBE Vector Graphic - Fill","hd":false},{"ty":"tr","p":{"a":0,"k":[0,0],"ix":2},"a":{"a":0,"k":[0,0],"ix":1},"s":{"a":0,"k":[100,100],"ix":3},"r":{"a":0,"k":0,"ix":6},"o":{"a":0,"k":100,"ix":7},"sk":{"a":0,"k":0,"ix":4},"sa":{"a":0,"k":0,"ix":5},"nm":"Transform"}],"nm":"Group 2","np":2,"cix":2,"bm":0,"ix":2,"mn":"ADBE Vector Group","hd":false},{"ty":"tr","p":{"a":0,"k":[0,0],"ix":2},"a":{"a":0,"k":[0,0],"ix":1},"s":{"a":0,"k":[100,100],"ix":3},"r":{"a":0,"k":0,"ix":6},"o":{"a":0,"k":100,"ix":7},"sk":{"a":0,"k":0,"ix":4},"sa":{"a":0,"k":0,"ix":5},"nm":"Transform"}],"nm":"Group 1","np":2,"cix":2,"bm":0,"ix":1,"mn":"ADBE Vector Group","hd":false},{"ty":"tr","p":{"a":0,"k":[0,0],"ix":2},"a":{"a":0,"k":[0,0],"ix":1},"s":{"a":0,"k":[100,100],"ix":3},"r":{"a":0,"k":0,"ix":6},"o":{"a":0,"k":100,"ix":7},"sk":{"a":0,"k":0,"ix":4},"sa":{"a":0,"k":0,"ix":5},"nm":"Transform"}],"nm":"Group 1","np":1,"cix":2,"bm":0,"ix":1,"mn":"ADBE Vector Group","hd":false},{"ty":"tr","p":{"a":0,"k":[0,0],"ix":2},"a":{"a":0,"k":[0,0],"ix":1},"s":{"a":0,"k":[100,100],"ix":3},"r":{"a":0,"k":0,"ix":6},"o":{"a":0,"k":100,"ix":7},"sk":{"a":0,"k":0,"ix":4},"sa":{"a":0,"k":0,"ix":5},"nm":"Transform"}],"nm":"Group 1","np":1,"cix":2,"bm":0,"ix":1,"mn":"ADBE Vector Group","hd":false},{"ty":"tr","p":{"a":0,"k":[0,0],"ix":2},"a":{"a":0,"k":[0,0],"ix":1},"s":{"a":0,"k":[100,100],"ix":3},"r":{"a":0,"k":0,"ix":6},"o":{"a":0,"k":100,"ix":7},"sk":{"a":0,"k":0,"ix":4},"sa":{"a":0,"k":0,"ix":5},"nm":"Transform"}],"nm":"Group 1","np":1,"cix":2,"bm":0,"ix":1,"mn":"ADBE Vector Group","hd":false},{"ty":"gr","it":[{"ind":0,"ty":"sh","ix":1,"ks":{"a":0,"k":{"i":[[20.303,12.861],[0,0],[0,0],[0,0],[0,0],[0,0],[0.005,-22.998],[11.698,-11.704],[17.852,-0.002],[11.704,11.698],[0.002,17.852],[-11.698,11.704],[-17.853,0.002],[0,0],[0.003,-40.074],[-40.072,-0.003],[-0.003,40.071]],"o":[[0,0],[0,0],[0,0],[0,0],[0,0],[18.097,11.45],[-0.002,17.852],[-11.704,11.698],[-17.853,-0.002],[-11.698,-11.704],[0.002,-17.854],[11.704,-11.697],[0,0],[-40.072,0.002],[0.003,40.071],[40.071,-0.003],[-0.005,-25.811]],"v":[[-239.463,63.189],[-235.473,56.95],[-241.62,56.101],[-266.888,52.608],[-249.793,79.341],[-243.746,69.886],[-213.624,124.517],[-232.547,170.199],[-278.23,189.122],[-323.914,170.199],[-342.837,124.517],[-323.914,78.833],[-278.23,59.911],[-278.23,51.963],[-350.785,124.517],[-278.23,197.07],[-205.676,124.517]],"c":true},"ix":2},"nm":"Path 1","mn":"ADBE Vector Shape - Group","hd":false},{"ty":"fl","c":{"a":0,"k":[0,0.215686276555,0.698039233685,1],"ix":4},"o":{"a":0,"k":100,"ix":5},"r":1,"bm":0,"nm":"Fill 1","mn":"ADBE Vector Graphic - Fill","hd":false},{"ty":"tr","p":{"a":0,"k":[0,0],"ix":2},"a":{"a":0,"k":[0,0],"ix":1},"s":{"a":0,"k":[100,100],"ix":3},"r":{"a":0,"k":0,"ix":6},"o":{"a":0,"k":100,"ix":7},"sk":{"a":0,"k":0,"ix":4},"sa":{"a":0,"k":0,"ix":5},"nm":"Transform"}],"nm":"Group 2","np":2,"cix":2,"bm":0,"ix":2,"mn":"ADBE Vector Group","hd":false},{"ty":"gr","it":[{"ty":"gr","it":[{"ind":0,"ty":"sh","ix":1,"ks":{"a":0,"k":{"i":[[0,-48.719],[48.719,0],[0,48.719],[-48.719,0]],"o":[[0,48.719],[-48.719,0],[0,-48.719],[48.719,0]],"v":[[-190.017,124.516],[-278.231,212.73],[-366.444,124.516],[-278.231,36.303]],"c":true},"ix":2},"nm":"Path 1","mn":"ADBE Vector Shape - Group","hd":false},{"ty":"fl","c":{"a":0,"k":[1,1,1,1],"ix":4},"o":{"a":0,"k":100,"ix":5},"r":1,"bm":0,"nm":"Fill 1","mn":"ADBE Vector Graphic - Fill","hd":false},{"ty":"tr","p":{"a":0,"k":[0,0],"ix":2},"a":{"a":0,"k":[0,0],"ix":1},"s":{"a":0,"k":[100,100],"ix":3},"r":{"a":0,"k":0,"ix":6},"o":{"a":0,"k":100,"ix":7},"sk":{"a":0,"k":0,"ix":4},"sa":{"a":0,"k":0,"ix":5},"nm":"Transform"}],"nm":"Group 1","np":2,"cix":2,"bm":0,"ix":1,"mn":"ADBE Vector Group","hd":false},{"ty":"tr","p":{"a":0,"k":[0,0],"ix":2},"a":{"a":0,"k":[0,0],"ix":1},"s":{"a":0,"k":[100,100],"ix":3},"r":{"a":0,"k":0,"ix":6},"o":{"a":0,"k":100,"ix":7},"sk":{"a":0,"k":0,"ix":4},"sa":{"a":0,"k":0,"ix":5},"nm":"Transform"}],"nm":"Group 3","np":1,"cix":2,"bm":0,"ix":3,"mn":"ADBE Vector Group","hd":false}],"ip":0,"op":84,"st":0,"bm":0},{"ddd":0,"ind":11,"ty":4,"nm":"...","parent":5,"sr":1,"ks":{"o":{"a":0,"k":100,"ix":11},"r":{"a":0,"k":0,"ix":10},"p":{"a":1,"k":[{"i":{"x":0.667,"y":1},"o":{"x":0.333,"y":0},"t":28,"s":[0,0,0],"to":[0,0,0],"ti":[0,0,0]},{"i":{"x":0.833,"y":1},"o":{"x":0.333,"y":0},"t":32,"s":[0,30,0],"to":[0,0,0],"ti":[0,0,0]},{"t":39,"s":[0,0,0]}],"ix":2,"l":2},"a":{"a":0,"k":[0,0,0],"ix":1,"l":2},"s":{"a":1,"k":[{"i":{"x":[0.833,0.833,0.833],"y":[1,1,1]},"o":{"x":[0.167,0.167,0.167],"y":[0,0,0]},"t":28,"s":[19,19,100]},{"t":39,"s":[100,100,100]}],"ix":6,"l":2}},"ao":0,"sy":[{"c":{"a":0,"k":[0,0,0,1],"ix":2},"o":{"a":0,"k":75,"ix":3},"a":{"a":0,"k":120,"ix":5},"s":{"a":0,"k":5,"ix":8},"d":{"a":0,"k":5,"ix":6},"ch":{"a":0,"k":0,"ix":7},"bm":{"a":0,"k":5,"ix":1},"no":{"a":0,"k":0,"ix":9},"lc":{"a":0,"k":1,"ix":10},"ty":1,"nm":"Drop Shadow"},{"c":{"a":0,"k":[0,0,0,1],"ix":2},"o":{"a":0,"k":75,"ix":3},"a":{"a":0,"k":120,"ix":5},"s":{"a":0,"k":5,"ix":8},"d":{"a":0,"k":5,"ix":6},"ch":{"a":0,"k":0,"ix":7},"bm":{"a":0,"k":5,"ix":1},"no":{"a":0,"k":0,"ix":9},"ty":2,"nm":"Inner Shadow"},{"c":{"a":0,"k":[1,1,0.745098039216,1],"ix":5},"o":{"a":0,"k":75,"ix":2},"s":{"a":0,"k":5,"ix":10},"r":{"a":0,"k":50,"ix":11},"ch":{"a":0,"k":0,"ix":9},"bm":{"a":0,"k":11,"ix":1},"no":{"a":0,"k":0,"ix":3},"j":{"a":0,"k":0,"ix":12},"ty":3,"nm":"Outer Glow"},{"c":{"a":0,"k":[1,1,0.745098039216,1],"ix":5},"o":{"a":0,"k":75,"ix":2},"s":{"a":0,"k":5,"ix":11},"r":{"a":0,"k":50,"ix":12},"sr":{"a":0,"k":1,"ix":9},"ch":{"a":0,"k":0,"ix":10},"bm":{"a":0,"k":11,"ix":1},"no":{"a":0,"k":0,"ix":3},"j":{"a":0,"k":0,"ix":13},"ty":4,"nm":"Inner Glow"},{"bs":{"a":0,"k":2,"ix":1},"bt":{"a":0,"k":1,"ix":2},"sr":{"a":0,"k":100,"ix":3},"bd":{"a":0,"k":1,"ix":4},"s":{"a":0,"k":5,"ix":5},"so":{"a":0,"k":75,"ix":15},"ga":{"a":0,"k":0,"ix":7},"a":{"a":0,"k":120,"ix":8},"ll":{"a":0,"k":30,"ix":9},"hm":{"a":0,"k":11,"ix":10},"hc":{"a":0,"k":[1,1,1,1],"ix":11},"ho":{"a":0,"k":75,"ix":12},"sm":{"a":0,"k":5,"ix":13},"sc":{"a":0,"k":[0,0,0,1],"ix":14},"ty":5,"nm":"Bevel and Emboss"},{"bm":{"a":0,"k":5,"ix":1},"c":{"a":0,"k":[0,0,0,1],"ix":2},"o":{"a":0,"k":50,"ix":3},"a":{"a":0,"k":19,"ix":4},"d":{"a":0,"k":11,"ix":5},"s":{"a":0,"k":14,"ix":6},"in":{"a":0,"k":1,"ix":7},"ty":6,"nm":"Satin"},{"bm":{"a":0,"k":1,"ix":1},"c":{"a":0,"k":[1,0,0,1],"ix":2},"so":{"a":0,"k":100,"ix":3},"ty":7,"nm":"Color Overlay"},{"bm":{"a":0,"k":1,"ix":1},"o":{"a":0,"k":100,"ix":2},"gf":{"a":0,"ix":3},"gs":{"a":0,"k":100,"ix":4},"a":{"a":0,"k":90,"ix":5},"gt":{"a":0,"k":1,"ix":6},"re":{"a":0,"k":0,"ix":7},"al":{"a":0,"k":1,"ix":8},"s":{"a":0,"k":100,"ix":9},"of":{"a":0,"k":[0,0],"ix":10},"ty":8,"nm":"Gradient Overlay"},{"c":{"a":0,"k":[1,0,0,1],"ix":2},"s":{"a":0,"k":3,"ix":3},"ty":0,"nm":"Stroke"}],"shapes":[{"ty":"gr","it":[{"ty":"gr","it":[{"ind":0,"ty":"sh","ix":1,"ks":{"a":0,"k":{"i":[[0,-3.049],[3.049,0],[0,3.049],[-3.049,0]],"o":[[0,3.049],[-3.049,0],[0,-3.049],[3.049,0]],"v":[[-204.246,-98.828],[-209.767,-93.307],[-215.288,-98.828],[-209.767,-104.349]],"c":true},"ix":2},"nm":"Path 1","mn":"ADBE Vector Shape - Group","hd":false},{"ty":"fl","c":{"a":0,"k":[0,0.827450990677,0.509803950787,1],"ix":4},"o":{"a":0,"k":100,"ix":5},"r":1,"bm":0,"nm":"Fill 1","mn":"ADBE Vector Graphic - Fill","hd":false},{"ty":"tr","p":{"a":0,"k":[0,0],"ix":2},"a":{"a":0,"k":[0,0],"ix":1},"s":{"a":0,"k":[100,100],"ix":3},"r":{"a":0,"k":0,"ix":6},"o":{"a":0,"k":100,"ix":7},"sk":{"a":0,"k":0,"ix":4},"sa":{"a":0,"k":0,"ix":5},"nm":"Transform"}],"nm":"Group 1","np":2,"cix":2,"bm":0,"ix":1,"mn":"ADBE Vector Group","hd":false},{"ty":"gr","it":[{"ind":0,"ty":"sh","ix":1,"ks":{"a":0,"k":{"i":[[0,-3.049],[3.049,0],[0,3.049],[-3.049,0]],"o":[[0,3.049],[-3.049,0],[0,-3.049],[3.049,0]],"v":[[-225.945,-98.828],[-231.466,-93.307],[-236.987,-98.828],[-231.466,-104.349]],"c":true},"ix":2},"nm":"Path 1","mn":"ADBE Vector Shape - Group","hd":false},{"ty":"fl","c":{"a":0,"k":[0,0.827450990677,0.509803950787,1],"ix":4},"o":{"a":0,"k":100,"ix":5},"r":1,"bm":0,"nm":"Fill 1","mn":"ADBE Vector Graphic - Fill","hd":false},{"ty":"tr","p":{"a":0,"k":[0,0],"ix":2},"a":{"a":0,"k":[0,0],"ix":1},"s":{"a":0,"k":[100,100],"ix":3},"r":{"a":0,"k":0,"ix":6},"o":{"a":0,"k":100,"ix":7},"sk":{"a":0,"k":0,"ix":4},"sa":{"a":0,"k":0,"ix":5},"nm":"Transform"}],"nm":"Group 2","np":2,"cix":2,"bm":0,"ix":2,"mn":"ADBE Vector Group","hd":false},{"ty":"gr","it":[{"ind":0,"ty":"sh","ix":1,"ks":{"a":0,"k":{"i":[[0,-3.049],[3.049,0],[0,3.049],[-3.049,0]],"o":[[0,3.049],[-3.049,0],[0,-3.049],[3.049,0]],"v":[[-247.644,-98.828],[-253.165,-93.307],[-258.686,-98.828],[-253.165,-104.349]],"c":true},"ix":2},"nm":"Path 1","mn":"ADBE Vector Shape - Group","hd":false},{"ty":"fl","c":{"a":0,"k":[0,0.827450990677,0.509803950787,1],"ix":4},"o":{"a":0,"k":100,"ix":5},"r":1,"bm":0,"nm":"Fill 1","mn":"ADBE Vector Graphic - Fill","hd":false},{"ty":"tr","p":{"a":0,"k":[0,0],"ix":2},"a":{"a":0,"k":[0,0],"ix":1},"s":{"a":0,"k":[100,100],"ix":3},"r":{"a":0,"k":0,"ix":6},"o":{"a":0,"k":100,"ix":7},"sk":{"a":0,"k":0,"ix":4},"sa":{"a":0,"k":0,"ix":5},"nm":"Transform"}],"nm":"Group 3","np":2,"cix":2,"bm":0,"ix":3,"mn":"ADBE Vector Group","hd":false},{"ty":"tr","p":{"a":0,"k":[0,0],"ix":2},"a":{"a":0,"k":[0,0],"ix":1},"s":{"a":0,"k":[100,100],"ix":3},"r":{"a":0,"k":0,"ix":6},"o":{"a":0,"k":100,"ix":7},"sk":{"a":0,"k":0,"ix":4},"sa":{"a":0,"k":0,"ix":5},"nm":"Transform"}],"nm":"Group 1","np":3,"cix":2,"bm":0,"ix":1,"mn":"ADBE Vector Group","hd":false},{"ty":"gr","it":[{"ty":"gr","it":[{"ind":0,"ty":"sh","ix":1,"ks":{"a":0,"k":{"i":[[0,11.578],[22.625,0],[0,-18.18],[-22.625,0],[-3.342,0.708],[0,0],[0,0]],"o":[[0,-18.18],[-22.625,0],[0,18.18],[3.618,0],[0,0],[0,0],[11.246,-5.868]],"v":[[-190.5,-98.828],[-231.466,-131.746],[-272.432,-98.828],[-231.466,-65.91],[-221.016,-67.032],[-206.497,-58.343],[-209.201,-71.22]],"c":true},"ix":2},"nm":"Path 1","mn":"ADBE Vector Shape - Group","hd":false},{"ty":"fl","c":{"a":0,"k":[0,0.215686276555,0.698039233685,1],"ix":4},"o":{"a":0,"k":100,"ix":5},"r":1,"bm":0,"nm":"Fill 1","mn":"ADBE Vector Graphic - Fill","hd":false},{"ty":"tr","p":{"a":0,"k":[0,0],"ix":2},"a":{"a":0,"k":[0,0],"ix":1},"s":{"a":0,"k":[100,100],"ix":3},"r":{"a":0,"k":0,"ix":6},"o":{"a":0,"k":100,"ix":7},"sk":{"a":0,"k":0,"ix":4},"sa":{"a":0,"k":0,"ix":5},"nm":"Transform"}],"nm":"Group 1","np":2,"cix":2,"bm":0,"ix":1,"mn":"ADBE Vector Group","hd":false},{"ty":"gr","it":[{"ind":0,"ty":"sh","ix":1,"ks":{"a":0,"k":{"i":[[0,-33.376],[33.376,0],[0,33.376],[-33.376,0]],"o":[[0,33.376],[-33.376,0],[0,-33.376],[33.376,0]],"v":[[-171.034,-98.828],[-231.466,-38.396],[-291.898,-98.828],[-231.466,-159.26]],"c":true},"ix":2},"nm":"Path 1","mn":"ADBE Vector Shape - Group","hd":false},{"ty":"fl","c":{"a":0,"k":[1,1,1,1],"ix":4},"o":{"a":0,"k":100,"ix":5},"r":1,"bm":0,"nm":"Fill 1","mn":"ADBE Vector Graphic - Fill","hd":false},{"ty":"tr","p":{"a":0,"k":[0,0],"ix":2},"a":{"a":0,"k":[0,0],"ix":1},"s":{"a":0,"k":[100,100],"ix":3},"r":{"a":0,"k":0,"ix":6},"o":{"a":0,"k":100,"ix":7},"sk":{"a":0,"k":0,"ix":4},"sa":{"a":0,"k":0,"ix":5},"nm":"Transform"}],"nm":"Group 2","np":2,"cix":2,"bm":0,"ix":2,"mn":"ADBE Vector Group","hd":false},{"ty":"tr","p":{"a":0,"k":[0,0],"ix":2},"a":{"a":0,"k":[0,0],"ix":1},"s":{"a":0,"k":[100,100],"ix":3},"r":{"a":0,"k":0,"ix":6},"o":{"a":0,"k":100,"ix":7},"sk":{"a":0,"k":0,"ix":4},"sa":{"a":0,"k":0,"ix":5},"nm":"Transform"}],"nm":"Group 2","np":2,"cix":2,"bm":0,"ix":2,"mn":"ADBE Vector Group","hd":false}],"ip":4,"op":84,"st":4,"bm":0}],"markers":[]}